[
    {
        "link": "https://childwelfare.gov",
        "Heading": "Child Welfare Information Gateway | Child Welfare Information Gateway",
        "Abstract": null,
        "Official Site": "https://childwelfare.gov",
        "Icon": "/favicon.ico",
        "Redirect": "https://childwelfare.gov",
        "AbstractSource": "BS4",
        "AbstractURL": "https://childwelfare.gov"
    },
    {
        "link": "https://thinkcrate.net",
        "Heading": "Edusphere",
        "Abstract": "",
        "Official Site": "https://thinkcrate.net",
        "Icon": "N/A",
        "Redirect": "https://thinkcrate.net",
        "AbstractSource": "BS4",
        "AbstractURL": "https://thinkcrate.net"
    },
    {
        "link": "https://gfireservers.in",
        "Heading": null,
        "Abstract": null,
        "Official Site": "https://gfireservers.in",
        "Icon": "N/A",
        "Redirect": "https://gfireservers.in",
        "AbstractSource": "BS4",
        "AbstractURL": "https://gfireservers.in"
    },
    {
        "link": "https://fatherly.com",
        "Heading": "Fatherly",
        "Abstract": "Fatherly empowers men to raise great kids and lead more fulfilling adult lives through original reporting, expert parenting advice, and hard-won insights into a challenging, but profoundly rewarding stage of life.",
        "Official Site": "https://www.fatherly.com",
        "Icon": "https://imgix.bustle.com/uploads/image/2022/5/16/4b070e39-b60a-473a-a36c-a0094c56ece7-socialshare-1.jpg?w=1200&h=630&fit=crop&crop=faces&fm=jpg",
        "Redirect": "https://www.fatherly.com",
        "AbstractSource": "BS4",
        "AbstractURL": "https://www.fatherly.com"
    },
    {
        "link": "https://hrworks.de",
        "Heading": "HR WORKS: Mehr Zeit f\u00fcr Menschen. Mehr Zeit f\u00fcr Erfolg.",
        "Abstract": "Die HR-Software f\u00fcr den Mittelstand. Wir glauben: Erfolg wird von Menschen gemacht.",
        "Official Site": "https://www.hrworks.de/",
        "Icon": "https://www.hrworks.de/wp-content/uploads/HRWORKS_OG-Image-_2025.png",
        "Redirect": "https://www.hrworks.de/",
        "AbstractSource": "BS4",
        "AbstractURL": "https://www.hrworks.de/"
    },
    {
        "link": "https://superpal.com",
        "Heading": "Uber Eats | Food & Grocery Delivery | Order Groceries and Food Online",
        "Abstract": "Find the best restaurants that deliver. Get contactless delivery for restaurant takeout, groceries, and more! Order food online or in the Uber Eats app and support local restaurants.",
        "Official Site": "https://www.ubereats.com/",
        "Icon": "https://tb-static.uber.com/prod/web-eats-v2/open-graph/uber-eats.jpg",
        "Redirect": "https://www.ubereats.com/",
        "AbstractSource": "BS4",
        "AbstractURL": "https://www.ubereats.com/"
    },
    {
        "link": "https://ccv.eu",
        "Heading": "Home | CCV EU",
        "Abstract": "Empowering payment. With over 65 years of experience, we offer every entrepreneur the best payment solution. From payment terminal to web shop payment.",
        "Official Site": "https://www.ccv.eu/en/home",
        "Icon": "https://www.ccv.eu/sites/default/files/styles/og_image/public/images/desktop/CCV%20from%20Fiserv%20logo%20vertical%20Homepage%20teaser_1.png?itok=HE2YvfEK",
        "Redirect": "https://www.ccv.eu/en/home",
        "AbstractSource": "BS4",
        "AbstractURL": "https://www.ccv.eu/en/home"
    },
    {
        "link": "https://workmagic.io",
        "Heading": "WorkMagic | Growth by Science",
        "Abstract": "Unlock your marketing's full potential with our marketing science and experiment platform. Optimize for incrementality with WorkMagic's Incrementality-based Attribution, built custom for each brand.",
        "Official Site": "https://www.workmagic.io/",
        "Icon": "https://framerusercontent.com/images/HROjeteAMo7n27khMjErsCXWM.jpg",
        "Redirect": "https://www.workmagic.io/",
        "AbstractSource": "BS4",
        "AbstractURL": "https://www.workmagic.io/"
    },
    {
        "link": "https://hromadske.ua",
        "Heading": "hromadske - \u041e\u0441\u0442\u0430\u043d\u043d\u0456 \u043d\u043e\u0432\u0438\u043d\u0438 \u0434\u043d\u044f, \u0432\u0441\u0456 \u043d\u0430\u0434\u0437\u0432\u0438\u0447\u0430\u0439\u043d\u0456 \u043d\u043e\u0432\u0438\u043d\u0438 \u0432 \u0423\u043a\u0440\u0430\u0457\u043d\u0456 \u0447\u0438\u0442\u0430\u0439\u0442e \u043d\u0430 hromadske",
        "Abstract": "\u041d\u043e\u0432\u0438\u043d\u0438 \u0432 \u0423\u043a\u0440\u0430\u0457\u043d\u0456 \u0456 \u0441\u0432\u0456\u0442\u0456. \u041d\u0430\u0434\u0437\u0432\u0438\u0447\u0430\u0439\u043d\u0456 \u043d\u043e\u0432\u0438\u043d\u0438 \u0441\u044c\u043e\u0433\u043e\u0434\u043d\u0456. \u0412\u0441\u0456 \u043d\u043e\u0432\u0438\u043d\u0438 \u0434\u043d\u044f. \u0421\u0443\u0441\u043f\u0456\u043b\u044c\u0441\u0442\u0432\u043e \u0442\u0430 \u043a\u0443\u043b\u044c\u0442\u0443\u0440\u0430. \u041f\u043e\u043b\u0456\u0442\u0438\u0447\u043d\u0456, \u0435\u043a\u043e\u043d\u043e\u043c\u0456\u0447\u043d\u0456, \u0441\u043f\u043e\u0440\u0442\u0438\u0432\u043d\u0456 \u043d\u043e\u0432\u0438\u043d\u0438. \u0427\u0438\u0442\u0430\u0439\u0442\u0435 \u043d\u0430 hromadske",
        "Official Site": "https://hromadske.ua",
        "Icon": "https://hromadske.ua/static/content/thumbs/1200x630/a/ed/nqtrp7---c1200x630x50px50p--03099bd70e41984f9cdbb1a9d3e1ceda.jpg",
        "Redirect": "https://hromadske.ua",
        "AbstractSource": "BS4",
        "AbstractURL": "https://hromadske.ua"
    },
    {
        "link": "https://urv.cat",
        "Heading": "Universitat Rovira i Virgili | The public university of Tarragona",
        "Abstract": "The URV is the public university of southern Catalonia, with deep roots in the region, an international vision, approachable teaching staff and excellent research.",
        "Official Site": "https://www.urv.cat/en/",
        "Icon": "https://www.urv.cat/media/img/urv-og.jpg",
        "Redirect": "https://www.urv.cat/en/",
        "AbstractSource": "BS4",
        "AbstractURL": "https://www.urv.cat/en/"
    },
    {
        "link": "https://landr.com",
        "Heading": "Create, Master and Release Music Like a Pro | LANDR",
        "Abstract": "LANDR gives you everything you need to turn listeners into lifelong fans: World-class AI mastering, global music distribution, 70+ pro plugins and 3M+ samples.",
        "Official Site": "https://landr.com",
        "Icon": "https://cdn.prod.website-files.com/66451c84f87c605764b3d93a/66967e028a6d3fc0ca154179_Favicon.png",
        "Redirect": "https://landr.com",
        "AbstractSource": "BS4",
        "AbstractURL": "https://landr.com"
    },
    {
        "link": "https://dentsu.com",
        "Heading": " Integrated Marketing Solutions & Agency Services | dentsu USA",
        "Abstract": "Dentsu is an integrated growth and transformation partner to the world\u2019s leading organizations. Founded in 1901 in Tokyo, Japan, and now present in approximately 120 countries.",
        "Official Site": "https://www.dentsu.com/",
        "Icon": "https://assets-eu-01.kc-usercontent.com/7bf8ef96-9447-0161-1923-3ac6929eb20f/c7f279b8-dce4-4bb8-85ae-7ad72d1222ef/sample-banner.jpg?q=75&fm=jpg&w=960",
        "Redirect": "https://www.dentsu.com/",
        "AbstractSource": "BS4",
        "AbstractURL": "https://www.dentsu.com/"
    },
    {
        "link": "https://hrb.tax",
        "Heading": null,
        "Abstract": null,
        "Official Site": "https://hrb.tax",
        "Icon": "/favicon.ico",
        "Redirect": "https://hrb.tax",
        "AbstractSource": "BS4",
        "AbstractURL": "https://hrb.tax"
    },
    {
        "link": "https://farrow-ball.com",
        "Heading": "Farrow & Ball | Handcrafted Paint and Wallpaper | Farrow & Ball",
        "Abstract": "Our carefully curated palette of 132 shades and range of handcrafted wallpaper will help you find the colours and patterns you love for your home",
        "Official Site": "https://www.farrow-ball.com/home",
        "Icon": "https://www.farrow-ball.com/media/favicon/stores/1/New_Favicon_2024.jpg",
        "Redirect": "https://www.farrow-ball.com/home",
        "AbstractSource": "BS4",
        "AbstractURL": "https://www.farrow-ball.com/home"
    },
    {
        "link": "https://tecmint.com",
        "Heading": "TecMint: Linux Howtos, Tutorials & Guides",
        "Abstract": "TecMint is the largest free Linux resource on the web, covering tutorials, commands, tools, and guides for sysadmins, DevOps engineers, and Linux beginners.",
        "Official Site": "https://www.tecmint.com/",
        "Icon": "https://www.tecmint.com/wp-content/uploads/2026/05/linux-tutorials-guides-tecmint.webp",
        "Redirect": "https://www.tecmint.com/",
        "AbstractSource": "BS4",
        "AbstractURL": "https://www.tecmint.com/"
    },
    {
        "link": "https://washingtoninstitute.org",
        "Heading": "Homepage | The Washington Institute",
        "Abstract": null,
        "Official Site": "https://www.washingtoninstitute.org/home",
        "Icon": "https://www.washingtoninstitute.org/modules/custom/newcity_customizations/newcity_customizations.info.yml/images/twi-default-social.jpg",
        "Redirect": "https://www.washingtoninstitute.org/home",
        "AbstractSource": "BS4",
        "AbstractURL": "https://www.washingtoninstitute.org/home"
    },
    {
        "link": "https://udl.cat",
        "Heading": "Universitat de Lleida",
        "Abstract": "Som una universitat p\u00fablica i de qualitat, pr\u00f2xima alhora que oberta al m\u00f3n; referent en formaci\u00f3, recerca i innovaci\u00f3; compromesa amb la cooperaci\u00f3 per al desenvolupament i la sostenibilitat, la just\u00edcia social i la igualtat d'oportunitats, i capdavantera en producci\u00f3 cient\u00edfica i cultural en m\u00faltiples \u00e0rees de coneixement",
        "Official Site": "https://www.udl.cat/ca/index.html",
        "Icon": "/favicon.ico",
        "Redirect": "https://www.udl.cat/ca/index.html",
        "AbstractSource": "BS4",
        "AbstractURL": "https://www.udl.cat/ca/index.html"
    },
    {
        "link": "https://on-running.com",
        "Heading": "On | Swiss Performance Running Shoes & Clothing",
        "Abstract": "Born in the Swiss Alps, On running shoes feature the first patented cushioning system which is activated only when you need it - during the landing.",
        "Official Site": "https://www.on.com/en-us/",
        "Icon": "/favicon.ico",
        "Redirect": "https://www.on.com/en-us/",
        "AbstractSource": "BS4",
        "AbstractURL": "https://www.on.com/en-us/"
    },
    {
        "link": "https://cricket.com.au",
        "Heading": "Home | cricket.com.au",
        "Abstract": "Live cricket coverage, live streaming, cricket highlights, live scores, breaking news, video, analysis and expert opinion.",
        "Official Site": "https://cricket.com.au",
        "Icon": "https://www.cricket.com.au/resources/ver/v1.28.16/assets/cricket-australia/share-card.jpg",
        "Redirect": "https://cricket.com.au",
        "AbstractSource": "BS4",
        "AbstractURL": "https://cricket.com.au"
    },
    {
        "link": "https://wgal.com",
        "Heading": "York, Lancaster and Harrisburg PA News, Weather and Sports - WGAL Channel 8",
        "Abstract": "Stay in the know with the top stories of the day. Get all the latest Harrisburg, Lancaster and York news, weather and sports from the WGAL News Team.",
        "Official Site": "https://www.wgal.com",
        "Icon": "https://kubrick.htvapps.com/htv-prod-media.s3.amazonaws.com/htv_default_image/wgal/top_image.png?resize=1200:*",
        "Redirect": "https://www.wgal.com",
        "AbstractSource": "BS4",
        "AbstractURL": "https://www.wgal.com"
    },
    {
        "link": "https://udesk.cn",
        "Heading": "\u6c83\u4e30\u79d1\u6280-Udesk-\u4e2d\u56fd\u4eba\u5de5\u667a\u80fd\u4e0e\u8425\u9500\u670d\u52a1\u89e3\u51b3\u65b9\u6848\u63d0\u4f9b\u5546",
        "Abstract": "\u6c83\u4e30\u79d1\u6280Udesk\u662f\u4e2d\u56fd\u4eba\u5de5\u667a\u80fd\u4e0e\u8425\u9500\u670d\u52a1\u89e3\u51b3\u65b9\u6848\u63d0\u4f9b\u5546\uff0c\u62e5\u6709Udesk\u3001GaussMind\u3001ServiceGo\u3001\u5fae\u4e30\u7b49\u56db\u5927\u4ea7\u54c1\u7ebf\uff0c\u5c06AI\u6280\u672f\u5e94\u7528\u5230\u4f01\u4e1a\u8425\u9500\u3001\u670d\u52a1\u53ca\u5185\u90e8\u5171\u4eab\u7b49\u5404\u4e2a\u573a\u666f\u3002",
        "Official Site": "https://udesk.cn",
        "Icon": "/images/index/udesk_fav.ico",
        "Redirect": "https://udesk.cn",
        "AbstractSource": "BS4",
        "AbstractURL": "https://udesk.cn"
    },
    {
        "link": "https://wordnik.com",
        "Heading": "Wordnik",
        "Abstract": "All the words",
        "Official Site": "https://www.wordnik.com",
        "Icon": "https://www.wordnik.com/img/wordnik-logo-300px.png",
        "Redirect": "https://www.wordnik.com",
        "AbstractSource": "BS4",
        "AbstractURL": "https://www.wordnik.com"
    },
    {
        "link": "https://viiequgl.com",
        "Heading": null,
        "Abstract": null,
        "Official Site": "https://viiequgl.com",
        "Icon": "N/A",
        "Redirect": "https://viiequgl.com",
        "AbstractSource": "BS4",
        "AbstractURL": "https://viiequgl.com"
    },
    {
        "link": "https://revistaforum.com.br",
        "Heading": "P\u00e1gina Inicial - Revista F\u00f3rum",
        "Abstract": "Descubra a trajet\u00f3ria da Revista F\u00f3rum, sua influ\u00eancia e legado na m\u00eddia brasileira desde 2001 at\u00e9 sua \u00faltima edi\u00e7\u00e3o em 2013.",
        "Official Site": "https://revistaforum.com.br/",
        "Icon": "https://revistaforum.com.br/wp-content/uploads/2025/12/favicon-1-150x150.png",
        "Redirect": "https://revistaforum.com.br/",
        "AbstractSource": "BS4",
        "AbstractURL": "https://revistaforum.com.br/"
    },
    {
        "link": "https://lipsum.com",
        "Heading": "Lorem Ipsum - All the facts - Lipsum generator",
        "Abstract": "Reference site about Lorem Ipsum, giving information on its origins, as well as a random Lipsum generator.",
        "Official Site": "https://lipsum.com",
        "Icon": "/favicon.ico",
        "Redirect": "https://lipsum.com",
        "AbstractSource": "BS4",
        "AbstractURL": "https://lipsum.com"
    },
    {
        "link": "https://amf-france.org",
        "Heading": "Autorit\u00e9 des march\u00e9s financiers : protection de l'\u00e9pargne, information des investisseurs, fonctionnement des march\u00e9s financiers | AMF",
        "Abstract": "L'Autorit\u00e9 des march\u00e9s financiers (AMF) veille \u00e0 la protection de l'\u00e9pargne, \u00e0 l'information des investisseurs et au bon fonctionnement des march\u00e9s financiers",
        "Official Site": "https://amf-france.org",
        "Icon": "https://www.amf-france.org//sites/institutionnel/files/logo/amf_immeuble_logo.jpg",
        "Redirect": "https://amf-france.org",
        "AbstractSource": "BS4",
        "AbstractURL": "https://amf-france.org"
    },
    {
        "link": "https://flash-dash.net",
        "Heading": "FlashDash Casino 2025: Exciting Games and Instant Wins!\ud83c\udfb0",
        "Abstract": "Join FlashDash Casino and have fun! Play FlashDash slots, poker, and more. \ud83c\udfb2 Enjoy fast payouts and get rewards!",
        "Official Site": "https://flash-dash.net/",
        "Icon": "N/A",
        "Redirect": "https://flash-dash.net/",
        "AbstractSource": "BS4",
        "AbstractURL": "https://flash-dash.net/"
    }
]