[
    {
        "link": "https://kraj.by",
        "Heading": "\u041f\u043e\u0441\u043b\u0435\u0434\u043d\u0438\u0435 \u043d\u043e\u0432\u043e\u0441\u0442\u0438 \u0420\u0435\u0441\u043f\u0443\u0431\u043b\u0438\u043a\u0438 \u0411\u0435\u043b\u0430\u0440\u0443\u0441\u044c \u0438 \u041c\u0438\u043d\u0441\u043a\u043e\u0439 \u043e\u0431\u043b\u0430\u0441\u0442\u0438",
        "Abstract": "\u0427\u0438\u0442\u0430\u0439 \u041a\u0440\u0430\u0439 \u0431\u0430\u0439 \u2013 \u0431\u0443\u0434\u044c \u0432 \u043a\u0443\u0440\u0441\u0435! \u041c\u044b \u0435\u0436\u0435\u0434\u043d\u0435\u0432\u043d\u043e \u043f\u0443\u0431\u043b\u0438\u043a\u0443\u0435\u043c \u043f\u043e\u0441\u043b\u0435\u0434\u043d\u0438\u0435 \u043d\u043e\u0432\u043e\u0441\u0442\u0438 \u0420\u0435\u0441\u043f\u0443\u0431\u043b\u0438\u043a\u0438 \u0411\u0435\u043b\u0430\u0440\u0443\u0441\u044c \u0438 \u041c\u0438\u043d\u0441\u043a\u043e\u0439 \u043e\u0431\u043b\u0430\u0441\u0442\u0438, \u0430 \u0442\u0430\u043a\u0436\u0435 \u0432\u0430\u043a\u0430\u043d\u0441\u0438\u0438 \u0438 \u0440\u0430\u0441\u043f\u0438\u0441\u0430\u043d\u0438\u0435 \u0442\u0440\u0430\u043d\u0441\u043f\u043e\u0440\u0442\u0430.",
        "Official Site": "https://kraj.by/home/",
        "Icon": "/favicon.ico?favicon.ab2c37b6.ico",
        "Redirect": "https://kraj.by/home/",
        "AbstractSource": "BS4",
        "AbstractURL": "https://kraj.by/home/"
    },
    {
        "link": "https://bmcedirect.ma",
        "Heading": "BMCE Direct | BANK OF AFRICA",
        "Abstract": "Acc\u00e9dez \u00e0 vos comptes et r\u00e9alisez vos transactions \u00e0 tout moment en toute s\u00e9curit\u00e9 et autonomie \u00e0 travers BMCE Direct.",
        "Official Site": "https://bmcedirect.ma",
        "Icon": "https://cdn.bmcedirect.ma/INGR/sd/bmce_2018/1.113.31/fr/images/std/favicons/favicon-32x32.png",
        "Redirect": "https://bmcedirect.ma",
        "AbstractSource": "BS4",
        "AbstractURL": "https://bmcedirect.ma"
    },
    {
        "link": "https://journoportfolio.com",
        "Heading": "Journo Portfolio \u2013 Portfolio Website Builder",
        "Abstract": "Journo Portfolio is the easiest way to build a professional online portfolio website to showcase your work and impress clients and employers",
        "Official Site": "https://www.journoportfolio.com/",
        "Icon": "https://static.journoportfolio.com/images/social/home-1.99472fd89a10.jpg",
        "Redirect": "https://www.journoportfolio.com/",
        "AbstractSource": "BS4",
        "AbstractURL": "https://www.journoportfolio.com/"
    },
    {
        "link": "https://lightless-sync.org",
        "Heading": "Lightless Sync",
        "Abstract": "Lightless Sync - Let others see you as you see yourself.",
        "Official Site": "https://lightless-sync.org",
        "Icon": "assets/Lightless_Discord_Logo.ico",
        "Redirect": "https://lightless-sync.org",
        "AbstractSource": "BS4",
        "AbstractURL": "https://lightless-sync.org"
    },
    {
        "link": "https://mercadocar.com.br",
        "Heading": "MercadoCar - O Shopping de Autope\u00e7as | MercadoCar",
        "Abstract": "A MercadoCar \u00e9 l\u00edder no varejo de autope\u00e7as, sendo um dos maiores e melhores vendedores de itens para ve\u00edculos em todo o mundo. H\u00e1 50 anos inovando, adotamos o formato de venda de autope\u00e7as diretamente para o consumidor final, focando sempre no encantamento do cliente, proporcionando uma jornada de compras agrad\u00e1vel, cheia de aten\u00e7\u00e3o e cuidado.",
        "Official Site": "https://mercadocar.com.br",
        "Icon": "/icons/icons_0/favicon-32x32.ico",
        "Redirect": "https://mercadocar.com.br",
        "AbstractSource": "BS4",
        "AbstractURL": "https://mercadocar.com.br"
    },
    {
        "link": "https://innocraft.cloud",
        "Heading": "Cloud-Hosted Matomo - Analytics Platform - Matomo",
        "Abstract": "Matomo's cloud-hosted service provides a secure and reliable analytics solution, while giving you 100% ownership of your data and privacy.",
        "Official Site": "https://fr.matomo.org/matomo-cloud/",
        "Icon": "https://fr.matomo.org/wp-content/uploads/2020/06/website-graphics-2020-v5-1-e1611111459689.png",
        "Redirect": "https://fr.matomo.org/matomo-cloud/",
        "AbstractSource": "BS4",
        "AbstractURL": "https://fr.matomo.org/matomo-cloud/"
    },
    {
        "link": "https://profilbaru.com",
        "Heading": "PROFIL BARU SEKOLAH - KAMPUS - DOSEN - PELAJAR",
        "Abstract": "Informasi Lengkap sekolah, kampus, dosen, pelajar di Indonesia",
        "Official Site": "https:/profilbaru.com",
        "Icon": "https://profilbaru.com/images/profilbaru.png",
        "Redirect": "https:/profilbaru.com",
        "AbstractSource": "BS4",
        "AbstractURL": "https:/profilbaru.com"
    },
    {
        "link": "https://soniaperonaci.it",
        "Heading": "Le ricette di Sonia Peronaci",
        "Abstract": "E' una ricetta ricca e sostanziosa, preparata per Carnevale a base di sugo di pomodoro, polpette di carne, uova, salsiccia e piselli.",
        "Official Site": "https://www.soniaperonaci.it/",
        "Icon": "https://www.soniaperonaci.it/wp-content/uploads/2016/07/Insalata-di-riso.jpg",
        "Redirect": "https://www.soniaperonaci.it/",
        "AbstractSource": "BS4",
        "AbstractURL": "https://www.soniaperonaci.it/"
    },
    {
        "link": "https://ich.org",
        "Heading": "ICH Official web site : ICH",
        "Abstract": null,
        "Official Site": "https://ich.org",
        "Icon": "favicon.ico",
        "Redirect": "https://ich.org",
        "AbstractSource": "BS4",
        "AbstractURL": "https://ich.org"
    },
    {
        "link": "https://wilkes.edu",
        "Heading": "Wilkes University",
        "Abstract": "Wilkes University prepares students for lifelong success on their terms. What do you want to do? At Wilkes, you will.",
        "Official Site": "https://www.wilkes.edu/index.aspx",
        "Icon": "/_images/wilkes-university.jpg",
        "Redirect": "https://www.wilkes.edu/index.aspx",
        "AbstractSource": "BS4",
        "AbstractURL": "https://www.wilkes.edu/index.aspx"
    },
    {
        "link": "https://dummyjson.com",
        "Heading": "DummyJSON - Free Fake REST API for Placeholder JSON Data",
        "Abstract": "DummyJSON provides a free fake REST API with placeholder JSON data for development, testing, and prototyping. Access realistic data quickly for your projects.",
        "Official Site": "https://dummyjson.com",
        "Icon": "https://dummyjson.com/public/img/meta.png",
        "Redirect": "https://dummyjson.com",
        "AbstractSource": "BS4",
        "AbstractURL": "https://dummyjson.com"
    },
    {
        "link": "https://vipvoice.io",
        "Heading": "\n\tManager Portal\t",
        "Abstract": null,
        "Official Site": "https://vipvoice.io",
        "Icon": "https://vipvoice.io/ns-api/?object=image&action=read&filename=favicon.gif&server=vipvoice.io",
        "Redirect": "https://vipvoice.io",
        "AbstractSource": "BS4",
        "AbstractURL": "https://vipvoice.io"
    },
    {
        "link": "https://playcanvas.com",
        "Heading": "PlayCanvas | Open Source WebGL & WebGPU Game Engine",
        "Abstract": "Build stunning games, 3D visualizations, AR/VR experiences and playable ads with PlayCanvas, the open source JavaScript engine powered by WebGL and WebGPU.",
        "Official Site": "https://playcanvas.com/",
        "Icon": "https://playcanvas.com/assets/images/og/playcanvas.png",
        "Redirect": "https://playcanvas.com/",
        "AbstractSource": "BS4",
        "AbstractURL": "https://playcanvas.com/"
    },
    {
        "link": "https://abileneisd.org",
        "Heading": "Client Challenge",
        "Abstract": null,
        "Official Site": "https://abileneisd.org",
        "Icon": "N/A",
        "Redirect": "https://abileneisd.org",
        "AbstractSource": "BS4",
        "AbstractURL": "https://abileneisd.org"
    },
    {
        "link": "https://biletbayisi.com",
        "Heading": "U\u00e7ak Bileti Fiyatlar\u0131, Ucuz U\u00e7ak Bileti Bul | BiletBayisi",
        "Abstract": "U\u00e7ak bileti fiyatlar\u0131n\u0131 kar\u015f\u0131la\u015ft\u0131r\u0131n, ucuz u\u00e7ak bileti bul, rezervasyon yap, sat\u0131n al. Yurt i\u00e7i ve yurtd\u0131\u015f\u0131 en ucuz u\u00e7ak biletleri i\u00e7in Biletbayisi",
        "Official Site": "https://www.biletbayisi.com",
        "Icon": "https://www.biletbayisi.com/static/site/images/favicon/android-icon-192x192.png",
        "Redirect": "https://www.biletbayisi.com",
        "AbstractSource": "BS4",
        "AbstractURL": "https://www.biletbayisi.com"
    },
    {
        "link": "https://riversideca.gov",
        "Heading": "Riverside, California | City of Arts & Innovation ",
        "Abstract": null,
        "Official Site": "https://riversideca.gov",
        "Icon": "https://www.riversideca.gov/sites/all/themes/city_of_riverside/favicon.ico",
        "Redirect": "https://riversideca.gov",
        "AbstractSource": "BS4",
        "AbstractURL": "https://riversideca.gov"
    },
    {
        "link": "https://leijonat.fi",
        "Heading": "Leijonat - Leijonat",
        "Abstract": "Leijonat",
        "Official Site": "https://www.leijonat.fi/",
        "Icon": "https://www.leijonat.fi/images/Suomi-logo-paavari-sininen-1500-1000.jpg",
        "Redirect": "https://www.leijonat.fi/",
        "AbstractSource": "BS4",
        "AbstractURL": "https://www.leijonat.fi/"
    },
    {
        "link": "https://bibliopolis.com",
        "Heading": "Bibliopolis | We build the tools of the trade",
        "Abstract": "BookRouter\u2122 powers robust ecommerce websites. Ask for a demonstration today",
        "Official Site": "https://bibliopolis.com",
        "Icon": "https://www.bibliopolis.com/images/home-responsive-preview.png",
        "Redirect": "https://bibliopolis.com",
        "AbstractSource": "BS4",
        "AbstractURL": "https://bibliopolis.com"
    },
    {
        "link": "https://active911.com",
        "Heading": "Helping Heroes Save Lives - Home - Active911",
        "Abstract": "Active911 helps heroes save lives with software designed to get first responders on scene faster with fast alerting, easy scheduling and more",
        "Official Site": "https://active911.com/",
        "Icon": "https://active911.com/wp-content/uploads/2022/10/Active911-favicon-honorgold-152.png",
        "Redirect": "https://active911.com/",
        "AbstractSource": "BS4",
        "AbstractURL": "https://active911.com/"
    },
    {
        "link": "https://league-one.jp",
        "Heading": "\u3010\u516c\u5f0f\u3011\u30b8\u30e3\u30d1\u30f3\u30e9\u30b0\u30d3\u30fc \u30ea\u30fc\u30b0\u30ef\u30f3 \u516c\u5f0f\u30b5\u30a4\u30c8",
        "Abstract": "JAPAN RUGBY LEAGUE ONE\uff08\u30ea\u30fc\u30b0\u30ef\u30f3\uff09\u516c\u5f0f\u30b5\u30a4\u30c8\u3067\u306f\u8a66\u5408\u901f\u5831\u3001\u30cb\u30e5\u30fc\u30b9\u30ea\u30ea\u30fc\u30b9\u3001\u65e5\u7a0b\u7d50\u679c\u3001\u9806\u4f4d\u3001\u30c1\u30fc\u30e0/\u9078\u624b\u60c5\u5831\u306a\u3069\u3092\u3054\u89a7\u3044\u305f\u3060\u3051\u307e\u3059\u3002",
        "Official Site": "https://league-one.jp/",
        "Icon": "https://league-one.s3.ap-northeast-1.amazonaws.com/image/site_info/16991_1200x630_68636b5fa7b86.png",
        "Redirect": "https://league-one.jp/",
        "AbstractSource": "BS4",
        "AbstractURL": "https://league-one.jp/"
    },
    {
        "link": "https://statuscake.com",
        "Heading": "StatusCake - Uptime monitoring, Page speed monitoring, and more",
        "Abstract": "Website Monitoring solution that drives revenue & keeps you online. Track your uptime, page speed, domain, server, & SSL certificates.",
        "Official Site": "https://www.statuscake.com/",
        "Icon": "https://www.statuscake.com/wp-content/uploads/2024/07/cs-og-img.png",
        "Redirect": "https://www.statuscake.com/",
        "AbstractSource": "BS4",
        "AbstractURL": "https://www.statuscake.com/"
    },
    {
        "link": "https://rajakomen.com",
        "Heading": "Jasa Buzzer Positif, Promosi di Media Sosial - RajaKomen.com",
        "Abstract": "MARKETPLACE yang mempertemukan freelancer dan pemilik akun media sosial instagram facebook youtube tiktok twitter",
        "Official Site": "https://rajakomen.com",
        "Icon": "https://rajakomen.com/tm_design/icon_webpage.png",
        "Redirect": "https://rajakomen.com",
        "AbstractSource": "BS4",
        "AbstractURL": "https://rajakomen.com"
    },
    {
        "link": "https://senler.ru",
        "Heading": "Senler \u2014 \u043a\u043e\u043d\u0441\u0442\u0440\u0443\u043a\u0442\u043e\u0440 \u0447\u0430\u0442-\u0431\u043e\u0442\u043e\u0432 \u0412\u041a\u043e\u043d\u0442\u0430\u043a\u0442\u0435",
        "Abstract": "Senler \u2014 \u044d\u0442\u043e \u0443\u0434\u043e\u0431\u043d\u0430\u044f \u043f\u043b\u0430\u0442\u0444\u043e\u0440\u043c\u0430 \u0434\u043b\u044f \u0441\u043e\u0437\u0434\u0430\u043d\u0438\u044f \u0447\u0430\u0442-\u0431\u043e\u0442\u043e\u0432 \u0438 \u0440\u0430\u0441\u0441\u044b\u043b\u043e\u043a \u043b\u0438\u0447\u043d\u044b\u0445 \u0441\u043e\u043e\u0431\u0449\u0435\u043d\u0438\u0439 \u0412\u041a\u043e\u043d\u0442\u0430\u043a\u0442\u0435 \u043e\u0442 \u0438\u043c\u0435\u043d\u0438 \u0441\u043e\u043e\u0431\u0449\u0435\u0441\u0442\u0432. \u041d\u0430\u0441\u0442\u0440\u0430\u0438\u0432\u0430\u0435\u043c\u044b\u0435 \u043f\u043e\u0434\u043f\u0438\u0441\u043d\u044b\u0435 \u0441\u0442\u0440\u0430\u043d\u0438\u0446\u044b \u0438 \u043f\u0435\u0440\u0441\u043e\u043d\u0430\u043b\u0438\u0437\u0430\u0446\u0438\u044f \u0441\u043e\u043e\u0431\u0449\u0435\u043d\u0438\u0439. \u0421\u0435\u0433\u043c\u0435\u043d\u0442\u0430\u0446\u0438\u044f \u043f\u043e\u0434\u043f\u0438\u0441\u0447\u0438\u043a\u043e\u0432 \u0438 \u0434\u0435\u0442\u0430\u043b\u044c\u043d\u0430\u044f \u0441\u0442\u0430\u0442\u0438\u0441\u0442\u0438\u043a\u0430 \u0434\u043b\u044f \u0430\u043d\u0430\u043b\u0438\u0437\u0430 \u044d\u0444\u0444\u0435\u043a\u0442\u0438\u0432\u043d\u043e\u0441\u0442\u0438.",
        "Official Site": "https://senler.ru",
        "Icon": "/web/images/logo.svg",
        "Redirect": "https://senler.ru",
        "AbstractSource": "BS4",
        "AbstractURL": "https://senler.ru"
    },
    {
        "link": "https://smartz.cloud",
        "Heading": "Smartz",
        "Abstract": "",
        "Official Site": "https://smartz.cloud",
        "Icon": "/static/favicon.ico",
        "Redirect": "https://smartz.cloud",
        "AbstractSource": "BS4",
        "AbstractURL": "https://smartz.cloud"
    },
    {
        "link": "https://brookfield.com",
        "Heading": "Homepage | Brookfield",
        "Abstract": "Brookfield is a leading global investment firm, investing on behalf of institutions and individuals around the world. Start your investment journey today.",
        "Official Site": "https://www.brookfield.com/homepage",
        "Icon": "/themes/custom/brookfield/images/favicon/favicon-32x32.png",
        "Redirect": "https://www.brookfield.com/homepage",
        "AbstractSource": "BS4",
        "AbstractURL": "https://www.brookfield.com/homepage"
    },
    {
        "link": "https://ifce.edu.br",
        "Heading": "\n            Home\n            \u2014 IFCE\n        ",
        "Abstract": "",
        "Official Site": "https://ifce.edu.br",
        "Icon": "/static/images/favicon.e5b85f98d812.png",
        "Redirect": "https://ifce.edu.br",
        "AbstractSource": "BS4",
        "AbstractURL": "https://ifce.edu.br"
    },
    {
        "link": "https://dnssearch.org",
        "Heading": "Stop Downtime & Business Disruption | Absolute Security",
        "Abstract": "Resilient cybersecurity for your devices, data, and security controls. Create an unbreakable connection to every endpoint, ensuring they are visible, protected, and compliant at all times. Absolute is the industry benchmark in endpoint resilience, factory-embedded by every major PC manufacturer including Dell, Lenovo, HP and 23 more.",
        "Official Site": "https://dnssearch.org",
        "Icon": "https://cdn.prod.website-files.com/66459e52a38339f2998b9eef/67e86d95d30872582fec9f67_Absolute%20OpenGraph.jpg",
        "Redirect": "https://dnssearch.org",
        "AbstractSource": "BS4",
        "AbstractURL": "https://dnssearch.org"
    },
    {
        "link": "https://samba242.com",
        "Heading": "Cassinos e Apostas Esportivas Seguras | Jogue nos Melhores Sites Brasileiros",
        "Abstract": "Aposte com confian\u00e7a em cassinos online e sites de apostas esportivas no Brasil. Oferecemos b\u00f4nus, odds vantajosas e uma experi\u00eancia segura de jogo.",
        "Official Site": "https://samba242.com",
        "Icon": "https://dz68qzgzvzly6.cloudfront.net/samba/uploads/setting/file/telegram_cover.png",
        "Redirect": "https://samba242.com",
        "AbstractSource": "BS4",
        "AbstractURL": "https://samba242.com"
    },
    {
        "link": "https://soeducador.com.br",
        "Heading": "Cursos Online para Educadores | S\u00d3EDUCADOR",
        "Abstract": "Cursos online para educadores com certificados v\u00e1lidos.",
        "Official Site": "https://soeducador.com.br/",
        "Icon": "https://soeducador.com.br/i.soeducador.com.br/assets/img/site/open-graph/default3.webp",
        "Redirect": "https://soeducador.com.br/",
        "AbstractSource": "BS4",
        "AbstractURL": "https://soeducador.com.br/"
    },
    {
        "link": "https://pg77x.vip",
        "Heading": "PG77X.com",
        "Abstract": "PG77X.com Fornecemos os jogos PG mais populares. Incont\u00e1veis vencedores j\u00e1 nasceram aqui. Venha comigo, pr\u00eamios milion\u00e1rios est\u00e3o \u00e0 sua espera.",
        "Official Site": "https://pg77x.vip",
        "Icon": "/img/og.jpg",
        "Redirect": "https://pg77x.vip",
        "AbstractSource": "BS4",
        "AbstractURL": "https://pg77x.vip"
    },
    {
        "link": "https://anpfiff.info",
        "Heading": "\n\twww.anpfiff.info - Lokalfu\u00c3\u009fball in Franken\n",
        "Abstract": "anpfiff.info ist das Onlineportal f\u00c3\u00bcr regionalen Fu\u00c3\u009fball in ganz Franken. Von der B-Klasse bis zur Regionalliga!",
        "Official Site": "https://anpfiff.info",
        "Icon": "/images/design/anpfiff/android-touch-icon-2.png",
        "Redirect": "https://anpfiff.info",
        "AbstractSource": "BS4",
        "AbstractURL": "https://anpfiff.info"
    },
    {
        "link": "https://educ.ar",
        "Heading": "Inicio | Educ.ar, portal educativo de la Secretar\u00eda de Educaci\u00f3n",
        "Abstract": "El portal educ.ar brinda recursos digitales y propuestas innovadoras para potenciar la educaci\u00f3n en todo el pa\u00eds.",
        "Official Site": "https://educ.ar",
        "Icon": "/favicon.ico",
        "Redirect": "https://educ.ar",
        "AbstractSource": "BS4",
        "AbstractURL": "https://educ.ar"
    },
    {
        "link": "https://anime-indo.lol",
        "Heading": "Animeindo - Nonton Streaming Anime Subtitle Indonesia",
        "Abstract": "Animeindo Adalah Tempat Nonton Streaming Anime Subtitle Indonesia Terlengkap Dan Terupdate Kualitas 240p 360p 480p 720p HD",
        "Official Site": "https://anime-indo.lol/",
        "Icon": "/favicon.png",
        "Redirect": "https://anime-indo.lol/",
        "AbstractSource": "BS4",
        "AbstractURL": "https://anime-indo.lol/"
    },
    {
        "link": "https://dias.com.gr",
        "Heading": "\u0394\u0399\u0391\u03a3 - \u0394\u03b9\u03b1\u03c4\u03c1\u03b1\u03c0\u03b5\u03b6\u03b9\u03ba\u03ac \u03a3\u03c5\u03c3\u03c4\u03ae\u03bc\u03b1\u03c4\u03b1 \u0391.\u0395.",
        "Abstract": "\u039a\u03b1\u03bb\u03c9\u03c3\u03ae\u03c1\u03b8\u03b1\u03c4\u03b5 \u03c3\u03c4\u03bf \u03b4\u03b9\u03b1\u03b4\u03b9\u03ba\u03c4\u03c5\u03b1\u03ba\u03cc \u03c4\u03cc\u03c0\u03bf \u03c4\u03b7\u03c2 \u03b5\u03c4\u03b1\u03b9\u03c1\u03b5\u03af\u03b1\u03c2 \u0394\u03b9\u03b1\u03c4\u03c1\u03b1\u03c0\u03b5\u03b6\u03b9\u03ba\u03ac \u03a3\u03c5\u03c3\u03c4\u03ae\u03bc\u03b1\u03c4\u03b1 \u0391.\u0395. (\u0394\u0399\u0391\u03a3 \u0391\u0395), \u03b7 \u03bf\u03c0\u03bf\u03af\u03b1 \u03b9\u03b4\u03c1\u03cd\u03b8\u03b7\u03ba\u03b5 \u03c4\u03bf 1989 \u03bc\u03b5 \u03c3\u03ba\u03bf\u03c0\u03cc \u03c4\u03b7\u03bd \u03b1\u03bd\u03ac\u03c0\u03c4\u03c5\u03be\u03b7 \u03ba\u03b1\u03b9 \u03bb\u03b5\u03b9\u03c4\u03bf\u03c5\u03c1\u03b3\u03af\u03b1 \u03c5\u03c0\u03b7\u03c1\u03b5\u03c3\u03b9\u03ce\u03bd \u03c0\u03bb\u03b7\u03c1\u03c9\u03bc\u03ce\u03bd \u03c0\u03c1\u03bf\u03c2 \u03cc\u03c6\u03b5\u03bb\u03bf\u03c2 \u03c4\u03bf\u03c5 \u03b5\u03bb\u03bb\u03b7\u03bd\u03b9\u03ba\u03bf\u03cd \u03c7\u03c1\u03b7\u03bc\u03b1\u03c4\u03bf\u03c0\u03b9\u03c3\u03c4\u03c9\u03c4\u03b9\u03ba\u03bf\u03cd \u03c3\u03c5\u03c3\u03c4\u03ae\u03bc\u03b1\u03c4\u03bf\u03c2.",
        "Official Site": "https://dias.com.gr",
        "Icon": "/imgs/favicons/favicon-32x32.png",
        "Redirect": "https://dias.com.gr",
        "AbstractSource": "BS4",
        "AbstractURL": "https://dias.com.gr"
    }
]