[
    {
        "link": "https://ezsitehost.com",
        "Heading": null,
        "Abstract": null,
        "Official Site": "https://ezsitehost.com",
        "Icon": "N/A",
        "Redirect": "https://ezsitehost.com",
        "AbstractSource": "BS4",
        "AbstractURL": "https://ezsitehost.com"
    },
    {
        "link": "https://fish.audio",
        "Heading": "Best AI Text To Speech & Free Voice Cloning | Fish Audio",
        "Abstract": "TTS and voice cloning with unmatched emotion control.",
        "Official Site": "https://fish.audio/",
        "Icon": "https://img.ogis.dev/?template=fish&logo=https%3A%2F%2Fdocs.fish.audio%2Flogo%2Fdark.png&title=Fish+Audio&description=TTS+and+voice+cloning+with+unmatched+emotion+control.&subtitle=The+Most+Expressive+AI+Speech",
        "Redirect": "https://fish.audio/",
        "AbstractSource": "BS4",
        "AbstractURL": "https://fish.audio/"
    },
    {
        "link": "https://zintrack.com",
        "Heading": "Plausible \u00b7 Web analytics",
        "Abstract": "A lightweight, non-intrusive alternative to Google Analytics.",
        "Official Site": "https://zintrack.com",
        "Icon": "/images/icon/plausible_favicon-9ba4fc88116ddbefd69681d7c1985553.png?vsn=d",
        "Redirect": "https://zintrack.com",
        "AbstractSource": "BS4",
        "AbstractURL": "https://zintrack.com"
    },
    {
        "link": "https://suitsupply.com",
        "Heading": "Men's Suits | Wedding, Formal & Custom Suits | SUITSUPPLY ",
        "Abstract": "Discover our wedding, formal suits, tuxedos, and custom suits crafted from premium Italian fabrics. Shop In-Store or Online.",
        "Official Site": "https://suitsupply.com/en-us/",
        "Icon": "https://cdn.suitsupply.com/image/upload/suitsupply/assets/ss19/favicons/android-chrome-256x256.png",
        "Redirect": "https://suitsupply.com/en-us/",
        "AbstractSource": "BS4",
        "AbstractURL": "https://suitsupply.com/en-us/"
    },
    {
        "link": "https://jobright.ai",
        "Heading": "Jobright: Your AI Job Search Copilot",
        "Abstract": "Discover your dream job with Jobright, your AI job search copilot. Find relevant opportunities tailored to your goals. Gain filtered matches, deep insights, and stay ahead with real-time company trends. Let Jobright find your perfect fit.",
        "Official Site": "https://jobright.ai/",
        "Icon": "https://jobright.ai/newimages/seo_logo.png",
        "Redirect": "https://jobright.ai/",
        "AbstractSource": "BS4",
        "AbstractURL": "https://jobright.ai/"
    },
    {
        "link": "https://playnet.it",
        "Heading": "Playnet",
        "Abstract": "Ogni cliente ha il diritto di comunicare, di esserci, di esprimere la propria unicit\u00e0. Siamo fieri di fornire le infrastrutture pi\u00f9 aggiornate e il livello.",
        "Official Site": "https://www.playnet.it/",
        "Icon": "https://www.playnet.it/wp-content/uploads/2017/11/home-e-interno.png",
        "Redirect": "https://www.playnet.it/",
        "AbstractSource": "BS4",
        "AbstractURL": "https://www.playnet.it/"
    },
    {
        "link": "https://alianza.com",
        "Heading": "Alianza: Cloud Communications Platform for Service Providers",
        "Abstract": "Whether you're a service provider launching voice for the first time or upgrading to a next-gen solution, Alianza's cloud communications platform is for you.",
        "Official Site": "https://www.alianza.com/",
        "Icon": "https://www.alianza.com/wp-content/uploads/2025/03/Alianza-Basic-Images-New.png",
        "Redirect": "https://www.alianza.com/",
        "AbstractSource": "BS4",
        "AbstractURL": "https://www.alianza.com/"
    },
    {
        "link": "https://gdemoi.ru",
        "Heading": "\u0421\u0438\u0441\u0442\u0435\u043c\u0430 GPS \u0413\u041b\u041e\u041d\u0410\u0421\u0421 \u043c\u043e\u043d\u0438\u0442\u043e\u0440\u0438\u043d\u0433\u0430 \u0438 \u0442\u0440\u0435\u043a\u0435\u0440\u044b \u2013 \u0413\u0434\u0435\u041c\u043e\u0438",
        "Abstract": "\u041e\u0444\u0438\u0446\u0438\u0430\u043b\u044c\u043d\u044b\u0439 \u0441\u0430\u0439\u0442 \u0441\u0435\u0440\u0432\u0438\u0441\u0430 GPS \u0413\u041b\u041e\u041d\u0410\u0421\u0421 \u043c\u043e\u043d\u0438\u0442\u043e\u0440\u0438\u043d\u0433\u0430 \u0413\u0434\u0435\u041c\u043e\u0438. \u0421\u0438\u0441\u0442\u0435\u043c\u0430 \u0434\u043b\u044f \u043e\u043d\u043b\u0430\u0439\u043d \u043a\u043e\u043d\u0442\u0440\u043e\u043b\u044f \u043c\u0435\u0441\u0442\u043e\u043f\u043e\u043b\u043e\u0436\u0435\u043d\u0438\u044f \u043b\u044e\u0434\u0435\u0439, \u0442\u0440\u0430\u043d\u0441\u043f\u043e\u0440\u0442\u0430, \u0433\u0440\u0443\u0437\u043e\u0432 \u0441 \u043f\u043e\u043c\u043e\u0449\u044c\u044e \u0442\u0440\u0435\u043a\u0435\u0440\u043e\u0432, \u043c\u0430\u044f\u043a\u043e\u0432 \u0438\u043b\u0438 \u043c\u043e\u0431\u0438\u043b\u044c\u043d\u044b\u0445 \u043f\u0440\u0438\u043b\u043e\u0436\u0435\u043d\u0438\u0439",
        "Official Site": "https://www.gdemoi.ru/",
        "Icon": "https://www.gdemoi.ru/wp-content/uploads/2025/09/og-image-1200-630.png",
        "Redirect": "https://www.gdemoi.ru/",
        "AbstractSource": "BS4",
        "AbstractURL": "https://www.gdemoi.ru/"
    },
    {
        "link": "https://the-numbers.com",
        "Heading": "The Numbers - Where Data and the Movie Business Meet",
        "Abstract": "The Numbers provides detailed movie financial analysis, including box office, DVD and Blu-ray sales reports, and release schedules.",
        "Official Site": "https://www.the-numbers.com/",
        "Icon": "https://www.the-numbers.com/site-images/favicon.ico",
        "Redirect": "https://www.the-numbers.com/",
        "AbstractSource": "BS4",
        "AbstractURL": "https://www.the-numbers.com/"
    },
    {
        "link": "https://cdntechone.com",
        "Heading": "Ad Fraud Detection and Prevention Features - ADEX",
        "Abstract": "Advertising fraud smart detection and protection tools for online businesses. Say goodbye to impressions and click fraud!",
        "Official Site": "https://cdntechone.com",
        "Icon": "N/A",
        "Redirect": "https://cdntechone.com",
        "AbstractSource": "BS4",
        "AbstractURL": "https://cdntechone.com"
    },
    {
        "link": "https://eurobyte.ru",
        "Heading": "\u0415\u0432\u0440\u043e\u0431\u0430\u0439\u0442 \u2014 \u043d\u0430\u0434\u0435\u0436\u043d\u044b\u0439 \u0438 \u0431\u044b\u0441\u0442\u0440\u044b\u0439 \u0432\u0435\u0431-\u0445\u043e\u0441\u0442\u0438\u043d\u0433 \u0434\u043b\u044f \u0441\u0430\u0439\u0442\u043e\u0432",
        "Abstract": "\u0423\u0441\u043b\u0443\u0433\u0438 \u043e\u0442 \u0445\u043e\u0441\u0442\u0438\u043d\u0433-\u043f\u0440\u043e\u0432\u0430\u0439\u0434\u0435\u0440\u0430 \u00ab\u0415\u0432\u0440\u043e\u0431\u0430\u0439\u0442\u00bb: \u0446\u0435\u043d\u044b, \u0442\u0430\u0440\u0438\u0444\u044b, \u0442\u0435\u0441\u0442\u043e\u0432\u044b\u0439 \u043f\u0435\u0440\u0438\u043e\u0434. \u0411\u0435\u0437\u043b\u0438\u043c\u0438\u0442\u043d\u044b\u0439 \u0442\u0440\u0430\u0444\u0438\u043a. \u0412\u0435\u0440\u0441\u0438\u0438 PHP \u043d\u0430 \u0432\u044b\u0431\u043e\u0440, MySQL. \ud83d\udcbb \u0414\u0430\u0442\u0430-\u0446\u0435\u043d\u0442\u0440\u044b \u0432 \u0420\u043e\u0441\u0441\u0438\u0438 \u0438 \u0415\u0432\u0440\u043e\u043f\u0435.",
        "Official Site": "https://eurobyte.ru/",
        "Icon": "/img/preview-logo.png",
        "Redirect": "https://eurobyte.ru/",
        "AbstractSource": "BS4",
        "AbstractURL": "https://eurobyte.ru/"
    },
    {
        "link": "https://uhamka.ac.id",
        "Heading": "Universitas Muhammadiyah Prof.Dr.Hamka",
        "Abstract": "Universitas Muhammadiyah Prof.Dr.Hamka",
        "Official Site": "https://uhamka.ac.id",
        "Icon": "/logoUhamka.png",
        "Redirect": "https://uhamka.ac.id",
        "AbstractSource": "BS4",
        "AbstractURL": "https://uhamka.ac.id"
    },
    {
        "link": "https://win630.com",
        "Heading": "Win63",
        "Abstract": null,
        "Official Site": "https://win630.com",
        "Icon": "data:image/png;base64,iVBORw0KGgoAAAANSUhEUgAAAAEAAAABCAYAAAAfFcSJAAAADUlEQVR42mNkYPhfDwAChwGA60e6kgAAAABJRU5ErkJggg==",
        "Redirect": "https://win630.com",
        "AbstractSource": "BS4",
        "AbstractURL": "https://win630.com"
    },
    {
        "link": "https://sydsvenskan.se",
        "Heading": "Sydsvenskan \u2013 Nyheter Dygnet Runt",
        "Abstract": "Sydsvenskan.se \u00e4r den ledande nyhetstidningen i Sk\u00e5ne och \u00d6resundsregionen",
        "Official Site": "https://www.sydsvenskan.se/",
        "Icon": "/assets/static/sydsvenskan/favicon.ico",
        "Redirect": "https://www.sydsvenskan.se/",
        "AbstractSource": "BS4",
        "AbstractURL": "https://www.sydsvenskan.se/"
    },
    {
        "link": "https://safetydetectives.com",
        "Heading": "10 Best Antivirus Software in 2026: Windows, Android, iOS, Mac",
        "Abstract": "We reviewed and compared the best antivirus software on the market in this top cybersecurity 2026 list. Find the best protection for you and your devices.",
        "Official Site": "https://www.safetydetectives.com/",
        "Icon": "https://www.safetydetectives.com/wp-content/themes/comparison/assets/img/share_image.png",
        "Redirect": "https://www.safetydetectives.com/",
        "AbstractSource": "BS4",
        "AbstractURL": "https://www.safetydetectives.com/"
    },
    {
        "link": "https://mb66e.ink",
        "Heading": "MB66 \u2013 Trang Ch\u1ee7 Ch\u00ednh Th\u1ee9c MB66.COM, MB66E.TOP Truy C\u1eadp Uy T\u00edn 2026",
        "Abstract": "Tr\u1ea3i nghi\u1ec7m t\u1ea1i MB66 - Casino tr\u1ef1c tuy\u1ebfn h\u00e0ng \u0111\u1ea7u v\u1edbi giao d\u1ecbch nhanh, b\u1ea3o m\u1eadt cao. \u0110\u0103ng k\u00fd, \u0111\u0103ng nh\u1eadp ngay \u0111\u1ec3 tr\u1ea3i nghi\u1ec7m c\u00e1c d\u1ecbch v\u1ee5 uy t\u00edn v\u00e0 \u0111\u1ec9nh cao.",
        "Official Site": "https://mb66e.ink",
        "Icon": "https://mb6661.net/MB66_Media/20250227155928.png",
        "Redirect": "https://mb66e.ink",
        "AbstractSource": "BS4",
        "AbstractURL": "https://mb66e.ink"
    },
    {
        "link": "https://blogpostie.com",
        "Heading": "Create a Free Private Blog",
        "Abstract": "We make it very easy to create a high-quality blog, Over 10,000 people use our free blog platform to bring their ideas to life.",
        "Official Site": "https://blogpostie.com",
        "Icon": "https://media.blogpostie.com/favicon.ico",
        "Redirect": "https://blogpostie.com",
        "AbstractSource": "BS4",
        "AbstractURL": "https://blogpostie.com"
    },
    {
        "link": "https://coconala.com",
        "Heading": "\u30b3\u30b3\u30ca\u30e9 - \u30d7\u30ed\u304c\u96c6\u307e\u308b\u65e5\u672c\u6700\u5927\u7d1a\u306e\u30b9\u30ad\u30eb\u30de\u30fc\u30b1\u30c3\u30c8",
        "Abstract": "\u30b3\u30b3\u30ca\u30e9\u306f\u3001\u3044\u308d\u3093\u306a\u30b8\u30e3\u30f3\u30eb\u306e\u300c\u4ed5\u4e8b\u300d\u3084\u300c\u76f8\u8ac7\u300d\u3092\u30cd\u30c3\u30c8\u30b7\u30e7\u30c3\u30d4\u30f3\u30b0\u306e\u3088\u3046\u306b\u65e9\u304f\u30fb\u7c21\u5358\u30fb\u304a\u30c8\u30af\u306b\u4f9d\u983c\u3067\u304d\u307e\u3059\uff01\u30ed\u30b4\u3084\u540d\u523a\u306a\u3069\u306e\u30c7\u30b6\u30a4\u30f3\u3001\u52d5\u753b\u30fb\u30b5\u30a4\u30c8\u5236\u4f5c\u3001\u304a\u60a9\u307f\u76f8\u8ac7\u306a\u3069\u3001\u30d3\u30b8\u30cd\u30b9\u3084\u30d7\u30e9\u30a4\u30d9\u30fc\u30c8\u3067\u81ea\u5206\u3067\u306f\u3067\u304d\u306a\u3044\u3053\u3068\u3092\u30d7\u30ed\u3084\u5c02\u9580\u5bb6\u306b\u4f9d\u983c\u3057\u307e\u305b\u3093\u304b\uff1fNo.1\u30b9\u30ad\u30eb\u30de\u30fc\u30b1\u30c3\u30c8\u306e\u30b3\u30b3\u30ca\u30e9\uff01",
        "Official Site": "https://coconala.com/",
        "Icon": "https://coconala.com/images/facebook.png",
        "Redirect": "https://coconala.com/",
        "AbstractSource": "BS4",
        "AbstractURL": "https://coconala.com/"
    },
    {
        "link": "https://cruzverde.cl",
        "Heading": null,
        "Abstract": "",
        "Official Site": "https://cruzverde.cl",
        "Icon": "assets/favicon/favicon-32x32.png",
        "Redirect": "https://cruzverde.cl",
        "AbstractSource": "BS4",
        "AbstractURL": "https://cruzverde.cl"
    },
    {
        "link": "https://authorstream.com",
        "Heading": null,
        "Abstract": null,
        "Official Site": "https://authorstream.com",
        "Icon": "N/A",
        "Redirect": "https://authorstream.com",
        "AbstractSource": "BS4",
        "AbstractURL": "https://authorstream.com"
    },
    {
        "link": "https://pcpop.com",
        "Heading": null,
        "Abstract": null,
        "Official Site": "https://pcpop.com",
        "Icon": "N/A",
        "Redirect": "https://pcpop.com",
        "AbstractSource": "BS4",
        "AbstractURL": "https://pcpop.com"
    },
    {
        "link": "https://srg-it.ru",
        "Heading": "SRG-IT",
        "Abstract": null,
        "Official Site": "http://srg-it.tech",
        "Icon": "https://static.tildacdn.com/tild3466-6363-4662-a266-313763633439/_social.jpg",
        "Redirect": "http://srg-it.tech",
        "AbstractSource": "BS4",
        "AbstractURL": "http://srg-it.tech"
    },
    {
        "link": "https://stellarium.org",
        "Heading": "Stellarium Astronomy Software",
        "Abstract": "Stellarium is a planetarium software that shows exactly what you see when you look up at the stars. It's easy to use, and free.",
        "Official Site": "https://stellarium.org",
        "Icon": "N/A",
        "Redirect": "https://stellarium.org",
        "AbstractSource": "BS4",
        "AbstractURL": "https://stellarium.org"
    },
    {
        "link": "https://dealroom.co",
        "Heading": "Dealroom.co | Mapping the world's tech ecosystems",
        "Abstract": "The global intelligence platform for startup ecosystems. Discover promising startups, track funding rounds, and map tech ecosystems globally.",
        "Official Site": "https://dealroom.co/",
        "Icon": "https://dealroom.co/images/dealroom-og-image.png",
        "Redirect": "https://dealroom.co/",
        "AbstractSource": "BS4",
        "AbstractURL": "https://dealroom.co/"
    },
    {
        "link": "https://adplatform.io",
        "Heading": "\n      \n        adplatform - the only digital advertising platform you need. \u00b7 \n      \n    ",
        "Abstract": "",
        "Official Site": "https://adplatform.io",
        "Icon": "N/A",
        "Redirect": "https://adplatform.io",
        "AbstractSource": "BS4",
        "AbstractURL": "https://adplatform.io"
    },
    {
        "link": "https://monkeyisland.xyz",
        "Heading": "Remnawave",
        "Abstract": "Remnawave Dashboard",
        "Official Site": "https://monkeyisland.xyz",
        "Icon": "/favicons/logo.svg",
        "Redirect": "https://monkeyisland.xyz",
        "AbstractSource": "BS4",
        "AbstractURL": "https://monkeyisland.xyz"
    },
    {
        "link": "https://frwd.energy",
        "Heading": "\u041e \u043d\u0430\u0441 | \u0424\u043e\u0440\u0432\u0430\u0440\u0434 \u042d\u043d\u0435\u0440\u0433\u043e",
        "Abstract": null,
        "Official Site": "https://frwd.energy/",
        "Icon": "/themes/custom/fortum_base/media/icons/favicon_forward_energ_32x32.png",
        "Redirect": "https://frwd.energy/",
        "AbstractSource": "BS4",
        "AbstractURL": "https://frwd.energy/"
    },
    {
        "link": "https://gimmesomeoven.com",
        "Heading": "Gimme Some Oven | Easy Recipes For Everyday Life",
        "Abstract": "Gimme Some Oven features easy, delicious recipes for everyday life \u2014 from weeknight dinners to quick breakfasts, desserts and more.",
        "Official Site": "https://www.gimmesomeoven.com/",
        "Icon": "https://gimmesomeoven.com/wp-content/uploads/2015/05/Oven-Baked-Chicken-Breast-Recipe-4-1.jpg",
        "Redirect": "https://www.gimmesomeoven.com/",
        "AbstractSource": "BS4",
        "AbstractURL": "https://www.gimmesomeoven.com/"
    },
    {
        "link": "https://kipa.co.il",
        "Heading": "\u05d7\u05d3\u05e9\u05d5\u05ea \u05db\u05d9\u05e4\u05d4 - \u05d7\u05d3\u05e9\u05d5\u05ea, \u05e4\u05d5\u05dc\u05d9\u05d8\u05d9\u05e7\u05d4, \u05db\u05e1\u05e3, \u05d0\u05d5\u05db\u05dc, \u05d8\u05dc\u05d5\u05d5\u05d9\u05d6\u05d9\u05d4, \u05d1\u05e8\u05e0\u05d6'\u05d4 \u05d5\u05e2\u05d5\u05d3 ",
        "Abstract": "\u05db\u05d9\u05e4\u05d4 - \u05d0\u05ea\u05e8 \u05d4\u05d7\u05d3\u05e9\u05d5\u05ea \u05d4\u05de\u05d5\u05d1\u05d9\u05dc \u05d1\u05e6\u05d9\u05d1\u05d5\u05e8 \u05d4\u05d3\u05ea\u05d9. \u05db\u05d0\u05df \u05ea\u05de\u05e6\u05d0\u05d5 \u05d7\u05d3\u05e9\u05d5\u05ea, \u05e2\u05d3\u05db\u05d5\u05e0\u05d9\u05dd, \u05d9\u05d4\u05d3\u05d5\u05ea, \u05e4\u05e8\u05e9\u05ea \u05e9\u05d1\u05d5\u05e2 \u05ea\u05e8\u05d1\u05d5\u05ea, \u05de\u05ea\u05db\u05d5\u05e0\u05d9\u05dd, \u05d4\u05d5\u05e8\u05d9\u05dd \u05d5\u05d9\u05dc\u05d3\u05d9\u05dd, \u05de\u05d5\u05d6\u05d9\u05e7\u05d4, \u05d1\u05e8\u05e0\u05d6\u05d4 \u05d3\u05ea\u05d9\u05ea \u05d5\u05e2\u05d5\u05d3",
        "Official Site": "https://www.kipa.co.il/",
        "Icon": "https://www.kipa.co.il/images/shareIcon2021.jpg",
        "Redirect": "https://www.kipa.co.il/",
        "AbstractSource": "BS4",
        "AbstractURL": "https://www.kipa.co.il/"
    },
    {
        "link": "https://waqi.info",
        "Heading": "World's Air Pollution: Real-time Air Quality Index",
        "Abstract": "How polluted is the air today? Check out the real-time air pollution map, for more than 80 countries.",
        "Official Site": "https://waqi.info/",
        "Icon": "https://waqi.info/images/worldmap.png",
        "Redirect": "https://waqi.info/",
        "AbstractSource": "BS4",
        "AbstractURL": "https://waqi.info/"
    },
    {
        "link": "https://p7prx5xn.com",
        "Heading": null,
        "Abstract": "\ud83c\udf81Join JiLiDD.COM, get a free random sign up bonus and withdraw it after one round of betting.",
        "Official Site": "p7prx5xn.com",
        "Icon": "https://upload.t-u-7-v.com/s2/1768897731567/seo.png",
        "Redirect": "p7prx5xn.com",
        "AbstractSource": "BS4",
        "AbstractURL": "p7prx5xn.com"
    }
]