[
    {
        "link": "https://passion-games.com",
        "Heading": "Passion Games - Gaming Intelligence",
        "Abstract": "Daily insights from the sharpest minds in online gaming, sweepstakes, and betting.",
        "Official Site": "https://passion-games.com",
        "Icon": "/images/passion-games-logo.svg",
        "Redirect": "https://passion-games.com",
        "AbstractSource": "BS4",
        "AbstractURL": "https://passion-games.com"
    },
    {
        "link": "https://momentohq.com",
        "Heading": "Home - Momento",
        "Abstract": "Enterprise cachingre-engineered for reliability Get Valkey, tuned and hardened by systems engineers who can run it hotter than anyone else. Talk to Us Global leaders trust Momento to operate caching at the limits. Why enterprises choose Momento not just faster caching. bullet-proof caching. Reliable Multi-AZ by default, zero-downtime upgrades Hot-key shielding to prevent cascading failures [\u2026]",
        "Official Site": "https://www.gomomento.com/",
        "Icon": "https://www.gomomento.com/wp-content/uploads/2025/09/Website-hero-img_v1-01.png",
        "Redirect": "https://www.gomomento.com/",
        "AbstractSource": "BS4",
        "AbstractURL": "https://www.gomomento.com/"
    },
    {
        "link": "https://exp.host",
        "Heading": null,
        "Abstract": null,
        "Official Site": "https://exp.host",
        "Icon": "N/A",
        "Redirect": "https://exp.host",
        "AbstractSource": "BS4",
        "AbstractURL": "https://exp.host"
    },
    {
        "link": "https://stuba.sk",
        "Heading": "Slovensk\u00e1 technick\u00e1 univerzita v Bratislave (STU)",
        "Abstract": "Slovensk\u00e1 technick\u00e1 univerzita v Bratislave (STU) - ofici\u00e1lna str\u00e1nka univerzity",
        "Official Site": "https://www.stuba.sk/",
        "Icon": "https://www.stuba.sk/buxus/assets/images/web/icons/stu_800.png",
        "Redirect": "https://www.stuba.sk/",
        "AbstractSource": "BS4",
        "AbstractURL": "https://www.stuba.sk/"
    },
    {
        "link": "https://expf.ru",
        "Heading": "EXPF Consulting",
        "Abstract": "\u041a\u043e\u043d\u0441\u0430\u043b\u0442\u0438\u043d\u0433 \u0432 \u043e\u0431\u043b\u0430\u0441\u0442\u0438 \u0430\u043d\u0430\u043b\u0438\u0437\u0430 \u0434\u0430\u043d\u043d\u044b\u0445",
        "Official Site": "https://expf.ru",
        "Icon": "https://static.tildacdn.com/tild3137-3663-4063-b432-343961383037/EXPF_Logo.svg",
        "Redirect": "https://expf.ru",
        "AbstractSource": "BS4",
        "AbstractURL": "https://expf.ru"
    },
    {
        "link": "https://ekartlogistics.com",
        "Heading": "EKL Grocery Dashboards",
        "Abstract": "Consumption-ui",
        "Official Site": "https://ekartlogistics.com",
        "Icon": "https://static-assets-web.flixcart.com/batman-returns/batman-returns/p/images/logo_lite-cbb357.png",
        "Redirect": "https://ekartlogistics.com",
        "AbstractSource": "BS4",
        "AbstractURL": "https://ekartlogistics.com"
    },
    {
        "link": "https://lumenlearning.com",
        "Heading": "Lumen Learning | Online Materials & Resources for Higher Ed",
        "Abstract": "Lumen Learning offers affordable digital courseware & professional development resources to enhance effective teaching and increase student success.",
        "Official Site": "https://lumenlearning.com/",
        "Icon": "https://lumenlearning.com/wp-content/uploads/2023/03/cropped-LumenLearning_Monogram_RGB@2x-1-32x32.png",
        "Redirect": "https://lumenlearning.com/",
        "AbstractSource": "BS4",
        "AbstractURL": "https://lumenlearning.com/"
    },
    {
        "link": "https://ifema.es",
        "Heading": "IFEMA MADRID: Eventos, Ferias y Congresos | IFEMA MADRID",
        "Abstract": "Creamos relaciones entre Personas Marcas y Experiencias! Ocio, turismo, arte, moda, tecnolog\u00eda, motor, educaci\u00f3n, empleo, gastronom\u00eda y \u00a1mucho m\u00e1s!",
        "Official Site": "https://www.ifema.es",
        "Icon": "https://www.ifema.es/img/ifema-madrid/rrss-ifema.jpg",
        "Redirect": "https://www.ifema.es",
        "AbstractSource": "BS4",
        "AbstractURL": "https://www.ifema.es"
    },
    {
        "link": "https://pace.edu",
        "Heading": "Pace University | Pace University New York",
        "Abstract": null,
        "Official Site": "https://pace.edu",
        "Icon": "/themes/custom/pace/favicon.ico",
        "Redirect": "https://pace.edu",
        "AbstractSource": "BS4",
        "AbstractURL": "https://pace.edu"
    },
    {
        "link": "https://ucas.com",
        "Heading": "Choose your future | UCAS",
        "Abstract": null,
        "Official Site": "https://ucas.com",
        "Icon": "/themes/custom/ucas/favicon.ico",
        "Redirect": "https://ucas.com",
        "AbstractSource": "BS4",
        "AbstractURL": "https://ucas.com"
    },
    {
        "link": "https://webcaster.pro",
        "Heading": "Webcaster.pro \u2013 \u041e\u043d\u043b\u0430\u0439\u043d-\u0432\u0438\u0434\u0435\u043e\u043f\u043b\u0430\u0442\u0444\u043e\u0440\u043c\u0430 \u0434\u043b\u044f \u0431\u0438\u0437\u043d\u0435\u0441\u0430",
        "Abstract": "\u0414\u043e\u0441\u0442\u0430\u0432\u043a\u0430, \u043c\u043e\u043d\u0435\u0442\u0438\u0437\u0430\u0446\u0438\u044f, \u0443\u043f\u0440\u0430\u0432\u043b\u0435\u043d\u0438\u0435, \u0437\u0430\u0449\u0438\u0442\u0430 \u0432\u0438\u0434\u0435\u043e\u043a\u043e\u043d\u0442\u0435\u043d\u0442\u0430. \u041f\u0440\u044f\u043c\u044b\u0435 \u0442\u0440\u0430\u043d\u0441\u043b\u044f\u0446\u0438\u0438 \u043d\u0430 \u0432\u0441\u0435\u0445 \u043f\u043b\u0430\u0442\u0444\u043e\u0440\u043c\u0430\u0445. \u0414\u043e\u0441\u0442\u0443\u043f \u043a API \u043f\u043b\u0430\u0442\u0444\u043e\u0440\u043c\u044b. \u0421\u043c\u0430\u0440\u0442\u0422\u0412. HTTP Live Streaming",
        "Official Site": "https://webcaster.pro",
        "Icon": "https://static.tildacdn.com/tild6337-3139-4362-b835-333064663934/4.jpg",
        "Redirect": "https://webcaster.pro",
        "AbstractSource": "BS4",
        "AbstractURL": "https://webcaster.pro"
    },
    {
        "link": "https://wpforms.com",
        "Heading": "WPForms - World's Leading WordPress AI Form Builder Plugin",
        "Abstract": "WPForms is the best AI-powered WordPress forms plugin, trusted by over 6,000,000+ users. Easily create powerful WordPress forms with our AI + drag & drop online form builder.",
        "Official Site": "https://wpforms.com/",
        "Icon": "https://wpforms.com/wp-content/uploads/2025/07/438836795_1061084875757096_8990436582237762163_n.png",
        "Redirect": "https://wpforms.com/",
        "AbstractSource": "BS4",
        "AbstractURL": "https://wpforms.com/"
    },
    {
        "link": "https://brunel.ac.uk",
        "Heading": "Brunel University of London",
        "Abstract": "A London campus university with a rich history of innovation. We offer courses that combine excellence in teaching and world-class research.",
        "Official Site": "https://brunel.ac.uk",
        "Icon": "/_MB34Eg_d3d57352-5d7b-4e70-b24e-6afe960b5815/static-main/img/icons/favicons/favicon.ico",
        "Redirect": "https://brunel.ac.uk",
        "AbstractSource": "BS4",
        "AbstractURL": "https://brunel.ac.uk"
    },
    {
        "link": "https://cftc.gov",
        "Heading": "Commodity Futures Trading Commission | CFTC",
        "Abstract": null,
        "Official Site": "https://cftc.gov",
        "Icon": "https://www.cftc.gov/sites/default/files/2025/06/1750109430/cftc-logo-square.png",
        "Redirect": "https://cftc.gov",
        "AbstractSource": "BS4",
        "AbstractURL": "https://cftc.gov"
    },
    {
        "link": "https://eko.com",
        "Heading": "Hands-on product capture for AI-powered shopping | eko",
        "Abstract": "Turn product data into interactive shopping experiences. Eko helps brands create dynamic product pages that boost engagement, trust, and conversions.",
        "Official Site": "https://eko.com/",
        "Icon": "https://framerusercontent.com/assets/Kjq45P0VhgEhhz0yamLhKdbZPRw.png",
        "Redirect": "https://eko.com/",
        "AbstractSource": "BS4",
        "AbstractURL": "https://eko.com/"
    },
    {
        "link": "https://grc.com",
        "Heading": "\u00a0\u00a0Home of Gibson Research Corporation\u00a0\u00a0",
        "Abstract": "Steve Gibson's and Gibson Research Corporation's Web homepage.",
        "Official Site": "https://grc.com",
        "Icon": "/apple-touch-icon.png",
        "Redirect": "https://grc.com",
        "AbstractSource": "BS4",
        "AbstractURL": "https://grc.com"
    },
    {
        "link": "https://bang-olufsen.com",
        "Heading": "Bang & Olufsen - High-end Headphones, Speakers, and Televisions",
        "Abstract": "Discover Bang & Olufsen \u2013 where sound meets design. Shop premium speakers, headphones, and televisions for home and travel.",
        "Official Site": "https://www.bang-olufsen.com/en/us",
        "Icon": "//images.ctfassets.net/8cd2csgvqd3m/49d68V5cfamsZb6GiC0swR/c1c0b6eec065d86a631c2c7d50f97088/t_i_2.jpg",
        "Redirect": "https://www.bang-olufsen.com/en/us",
        "AbstractSource": "BS4",
        "AbstractURL": "https://www.bang-olufsen.com/en/us"
    },
    {
        "link": "https://win-rar.com",
        "Heading": "WinRAR download free and support: WinRAR",
        "Abstract": "WinRAR - the data compression, encryption and archiving tool for Windows that opens RAR and ZIP files. Compatible with many other file formats.",
        "Official Site": "https://www.win-rar.com/start.html",
        "Icon": "https://www.win-rar.com/fileadmin/images/common/winrar-gui.png",
        "Redirect": "https://www.win-rar.com/start.html",
        "AbstractSource": "BS4",
        "AbstractURL": "https://www.win-rar.com/start.html"
    },
    {
        "link": "https://raceresult.com",
        "Heading": "RACE RESULT - Timing and Scoring of Sports Events",
        "Abstract": "RACE RESULT offers the complete timing and registration solution for sports events: from timing systems, transponders and race numbers to online registration and scoring software \u2013 used in 120+ countries.",
        "Official Site": "https://www.raceresult.com/en-us/home/index",
        "Icon": "https://images.raceresult.com/website/gen/RACE_RESULT_Logo_OG.png",
        "Redirect": "https://www.raceresult.com/en-us/home/index",
        "AbstractSource": "BS4",
        "AbstractURL": "https://www.raceresult.com/en-us/home/index"
    },
    {
        "link": "https://marquette.edu",
        "Heading": "Marquette University // Be The Difference",
        "Abstract": "Marquette University is a Catholic, Jesuit university located in Milwaukee, Wisconsin, that offers more than 80 majors through its nationally and internationally recognized colleges and schools.",
        "Official Site": "https://www.marquette.edu/",
        "Icon": "https://www.marquette.edu/_images/students-campus-og.jpg",
        "Redirect": "https://www.marquette.edu/",
        "AbstractSource": "BS4",
        "AbstractURL": "https://www.marquette.edu/"
    },
    {
        "link": "https://sarhne.com",
        "Heading": " \u0635\u0627\u0631\u062d\u0646\u064a - sarahah - \u0635\u0631\u0627\u062d\u0647 \u062f\u062e\u0648\u0644 ",
        "Abstract": "\u0645\u0648\u0642\u0639 \u0635\u0627\u0631\u062d\u0646\u064a , \u0645\u0646\u0635\u0629 \u062a\u0648\u0627\u0635\u0644 \u0627\u062c\u062a\u0645\u0627\u0639\u064a \u062a\u062a\u064a\u062d \u0644\u0644\u0645\u0633\u062a\u062e\u062f\u0645\u064a\u0646 \u0625\u0631\u0633\u0627\u0644 \u0631\u0633\u0627\u0626\u0644 \u0648\u0623\u0633\u0626\u0644\u0629 \u0645\u062c\u0647\u0648\u0644\u0629 \u0627\u0644\u0645\u0635\u062f\u0631. \u0633\u062c\u0644 \u062d\u0633\u0627\u0628\u0643 \u0645\u062c\u0627\u0646\u0646\u0627\u064b \u0648\u0627\u062d\u0635\u0644 \u0639\u0644\u0649 \u0631\u0627\u0628\u0637 \u0635\u0627\u0631\u062d\u0646\u064a \u0631\u0633\u0627\u0644\u0629 \u0633\u0631\u064a\u0647",
        "Official Site": "https://www.sarhne.com/",
        "Icon": "https://www.sarhne.com/blog/media/2021-04-02-386987838.webp",
        "Redirect": "https://www.sarhne.com/",
        "AbstractSource": "BS4",
        "AbstractURL": "https://www.sarhne.com/"
    },
    {
        "link": "https://katu.com",
        "Heading": "Portland News, Weather, Sports, Breaking News",
        "Abstract": "KATU ABC 2 offers coverage of news, weather, sports and community events for Portland, Oregon and surrounding towns, including Beaverton, Lake Oswego, Milwaukie, Happy Valley, Gresham, Vancouver, Hillsboro, Oregon City, Tualatin, West Linn, Woodburn, Tigard, Tualatin and Garden Home.",
        "Official Site": "https://katu.com",
        "Icon": "https://katu.com/resources/assets/katu/images/brand-icons/KATU-16x9.jpg",
        "Redirect": "https://katu.com",
        "AbstractSource": "BS4",
        "AbstractURL": "https://katu.com"
    },
    {
        "link": "https://nan-net.com",
        "Heading": "\u30a2\u30c0\u30eb\u30c8\u63b2\u793a\u677f \u30ca\u30f3\u30cd\u30c3\u30c8",
        "Abstract": "\u65e5\u672c\u6700\u5927\u306e\u30a2\u30c0\u30eb\u30c8\u63b2\u793a\u677f\u3010\u30ca\u30f3\u30cd\u30c3\u30c8\u3011\u306f\u3001\u9732\u51fa\u30fb\u5bdd\u53d6\u3089\u308c\u30fb\u8fd1\u89aa\u76f8\u59e6\u30fbSM\u306a\u3069\u69d8\u3005\u306a\u6027\u7656\u3092\u3082\u3064\u7d33\u58eb\u6dd1\u5973\u306e\u7686\u69d8\u306b20\u5e74\u4ee5\u4e0a\u611b\u3055\u308c\u3066\u3044\u308b\u793e\u4ea4\u5834\u3067\u3059\u3002\u30a8\u30c3\u30c1\u306a\u4f53\u9a13\u8ac7\u3001\u7d20\u4eba\u306e\u30a8\u30ed\u52d5\u753b\u6295\u7a3f\u3084\u30d5\u30a7\u30c1\u753b\u50cf\u3001\u610f\u898b\u4ea4\u63db\u306a\u3069\u30b3\u30df\u30e5\u30cb\u30c6\u30a3\u306f\u6d3b\u767a\u306b\u66f4\u65b0\u3055\u308c\u7d9a\u3051\u3066\u3044\u307e\u3059\u3002\u7121\u6599\u306e\u30ca\u30f3\u30cd\u30c3\u30c8ID SNS\u30b5\u30fc\u30d3\u30b9\u3068\u306e\u9023\u643a\u3067\u3055\u3089\u306b\u4fbf\u5229\u306b\u5229\u7528\u53ef\u80fd\u3002",
        "Official Site": "https://nan-net.com/",
        "Icon": "https://nan-net.com/img/twittercard.jpg",
        "Redirect": "https://nan-net.com/",
        "AbstractSource": "BS4",
        "AbstractURL": "https://nan-net.com/"
    },
    {
        "link": "https://kotak.bank.in",
        "Heading": "Savings Accounts, Personal Loans and Credit Cards - Kotak Mahindra Bank",
        "Abstract": "Kotak Mahindra Bank, India\u2019s trusted bank offers personal & business banking services - accounts, deposits, loans, cards, insurance, investments & more.",
        "Official Site": "https://www.kotak.bank.in/en/home.html",
        "Icon": "https://www.kotak.bank.in/content/dam/Kotak/herosliderbanner/zero-joining-fee-d.jpg",
        "Redirect": "https://www.kotak.bank.in/en/home.html",
        "AbstractSource": "BS4",
        "AbstractURL": "https://www.kotak.bank.in/en/home.html"
    },
    {
        "link": "https://lancaster.ac.uk",
        "Heading": "Home - Lancaster University",
        "Abstract": "Lancaster University is among the best in the UK. A top 10 UK university, we are also highly ranked in international league tables such as the QS World Rankings.",
        "Official Site": "https://www.lancaster.ac.uk/",
        "Icon": "https://www.lancaster.ac.uk/media/lancaster-university/content-assets/images/landing-page-images/StudentsbytheConfuciusCentre-desktop.jpg",
        "Redirect": "https://www.lancaster.ac.uk/",
        "AbstractSource": "BS4",
        "AbstractURL": "https://www.lancaster.ac.uk/"
    },
    {
        "link": "https://freecycle.org",
        "Heading": "Freecycle: Front Door",
        "Abstract": null,
        "Official Site": "https://freecycle.org",
        "Icon": "N/A",
        "Redirect": "https://freecycle.org",
        "AbstractSource": "BS4",
        "AbstractURL": "https://freecycle.org"
    },
    {
        "link": "https://chroniclelive.co.uk",
        "Heading": "Chronicle Live: Number one for news, opinion, sport & celebrity news",
        "Abstract": "Get the latest Newcastle news and North East news from the Evening Chronicle. Local website with breaking news, NUFC news, SAFC news, video, sport and weather from Newcastle and the North East region.",
        "Official Site": "https://www.chroniclelive.co.uk",
        "Icon": "https://www.chroniclelive.co.uk/nav-web-static/main-703c5efa6ab4b5ce08606b33ed23ef9d426ec5cb/public/assets/nechronicle/logos/logo-nechronicle-social-sharing.png",
        "Redirect": "https://www.chroniclelive.co.uk",
        "AbstractSource": "BS4",
        "AbstractURL": "https://www.chroniclelive.co.uk"
    }
]