[
    {
        "link": "https://kazakhstan-agro.kz",
        "Heading": "\u041f\u0438\u043d \u0410\u043f \u041a\u0430\u0437\u0438\u043d\u043e \u041a\u0430\u0437\u0430\u0445\u0441\u0442\u0430\u043d: \u043e\u0444\u0438\u0446\u0438\u0430\u043b\u044c\u043d\u044b\u0439 \u0441\u0430\u0439\u0442, \u0431\u043e\u043d\u0443\u0441\u044b \u0438 \u0432\u0445\u043e\u0434 \u0432 Pin Up KZ",
        "Abstract": null,
        "Official Site": "https://kazakhstan-agro.kz",
        "Icon": "/img/favicon.ico",
        "Redirect": "https://kazakhstan-agro.kz",
        "AbstractSource": "BS4",
        "AbstractURL": "https://kazakhstan-agro.kz"
    },
    {
        "link": "https://foulabook.com",
        "Heading": "\u0645\u0646\u0635\u0629 \u0627\u0644\u0642\u0631\u0627\u0621\u0629 \u0627\u0644\u0642\u0627\u0646\u0648\u0646\u064a\u0629 \u0644\u0644\u0643\u062a\u0628 - \u0641\u0648\u0644\u0629 \u0628\u0648\u0643",
        "Abstract": "\u0641\u0648\u0644\u0629 \u0628\u0648\u0643 | \u0645\u0646\u0635\u0629 \u0627\u0644\u0642\u0631\u0627\u0621\u0629 \u0627\u0644\u0642\u0627\u0646\u0648\u0646\u064a\u0629: \u0645\u0643\u062a\u0628\u062a\u0643 \u0644\u0642\u0631\u0627\u0621\u0629 \u0648\u0645\u0631\u0627\u062c\u0639\u0629 \u0622\u0644\u0627\u0641 \u0627\u0644\u0643\u062a\u0628 \u0627\u0644\u0639\u0631\u0628\u064a\u0629 \u0648\u0627\u0644\u0645\u062a\u0631\u062c\u0645\u0629 \u0623\u0648\u0646\u0644\u0627\u064a\u0646. \u0627\u0643\u062a\u0634\u0641 \u0627\u0644\u0645\u0644\u062e\u0635\u0627\u062a \u0648\u0627\u0644\u0625\u0635\u062f\u0627\u0631\u0627\u062a \u0627\u0644\u062c\u062f\u064a\u062f\u0629. \u0646\u0644\u062a\u0632\u0645 \u0628\u062d\u0642\u0648\u0642 \u0627\u0644\u0646\u0634\u0631 \u0648\u0646\u0648\u0641\u0631 \u0627\u0644\u0643\u062a\u0628 \u0627\u0644\u0645\u0631\u062e\u0635\u0629 \u0648\u0627\u0644\u0642\u0627\u0646\u0648\u0646\u064a\u0629 \u0641\u0642\u0637.",
        "Official Site": "https://foulabook.com",
        "Icon": "https://foulabook.com/images/foulabook.jpg",
        "Redirect": "https://foulabook.com",
        "AbstractSource": "BS4",
        "AbstractURL": "https://foulabook.com"
    },
    {
        "link": "https://ekispert.net",
        "Heading": "\u7d4c\u8def\u691c\u7d22 | \u99c5\u3059\u3071\u3042\u3068 for web",
        "Abstract": "\u7d4c\u8def\u691c\u7d22\u306f\u300e\u99c5\u3059\u3071\u3042\u3068 for web\u300f\u3002\u65e5\u672c\u5168\u56fd\u306e\u96fb\u8eca\u30fb\u8def\u7dda\u30d0\u30b9\u30fb\u9ad8\u901f\u30d0\u30b9\u30fb\u98db\u884c\u6a5f\u30fb\u30d5\u30a7\u30ea\u30fc\u3092\u4f7f\u7528\u3057\u305f\u7d4c\u8def\u691c\u7d22\u306b\u5bfe\u5fdc\u3002\u5b9a\u671f\u4ee3\u3084\u6642\u523b\u8868\u3001\u904b\u884c\u60c5\u5831\u3082\u7c21\u5358\u306b\u691c\u7d22\u3067\u304d\u307e\u3059\u3002",
        "Official Site": "https://ekispert.net",
        "Icon": "https://roote.ekispert.net/images/common/ogp.png",
        "Redirect": "https://ekispert.net",
        "AbstractSource": "BS4",
        "AbstractURL": "https://ekispert.net"
    },
    {
        "link": "https://purecars.com",
        "Heading": "PureCars \u2014 Automotive Digital Marketing & Business Intelligence For Dealers",
        "Abstract": "PureCars is the leading provider of automotive marketing services for car dealers. Digital advertising, customer data platform, market data.",
        "Official Site": "https://purecars.com",
        "Icon": "https://cdn.prod.website-files.com/65127cb7fcc53ebac9216eed/652995c025ad9713c855b641_Meta%20Image.png",
        "Redirect": "https://purecars.com",
        "AbstractSource": "BS4",
        "AbstractURL": "https://purecars.com"
    },
    {
        "link": "https://skolaonline.cz",
        "Heading": "Making sure you're not a bot!",
        "Abstract": null,
        "Official Site": "https://skolaonline.cz",
        "Icon": "N/A",
        "Redirect": "https://skolaonline.cz",
        "AbstractSource": "BS4",
        "AbstractURL": "https://skolaonline.cz"
    },
    {
        "link": "https://medicaldialogues.in",
        "Heading": "Medical News, Health News Latest, Medical News Today - Medical Dialogues |",
        "Abstract": "Medical News, Health News Latest, Medical News Today, Health News of India.",
        "Official Site": "https://medicaldialogues.in/",
        "Icon": "https://medicaldialogues.in/images/logo.png",
        "Redirect": "https://medicaldialogues.in/",
        "AbstractSource": "BS4",
        "AbstractURL": "https://medicaldialogues.in/"
    },
    {
        "link": "https://zoo.zone",
        "Heading": "zoo.zone",
        "Abstract": null,
        "Official Site": "https://zoo.zone",
        "Icon": "maug.png",
        "Redirect": "https://zoo.zone",
        "AbstractSource": "BS4",
        "AbstractURL": "https://zoo.zone"
    },
    {
        "link": "https://kasanova.com",
        "Heading": "Kasanova - Casalinghi, Arredamento e Tessile",
        "Abstract": "Scopri la selezione Kasanova di casalinghi, arredamento e tessile. Spedizione Gratuita per ordini superiori ai 59\u20ac, ritiro e reso gratuito in negozio.",
        "Official Site": "https://www.kasanova.com/it",
        "Icon": "https://www.kasanova.com/media/og_image/default/logo.jpg",
        "Redirect": "https://www.kasanova.com/it",
        "AbstractSource": "BS4",
        "AbstractURL": "https://www.kasanova.com/it"
    },
    {
        "link": "https://smartrecovery.org",
        "Heading": "SMART Recovery - Addiction Recovery Support",
        "Abstract": "SMART Recovery is the leading evidence-based addiction recovery program. Join a free meeting today and begin experiencing a Life Beyond Addiction.",
        "Official Site": "https://smartrecovery.org",
        "Icon": "https://smartrecovery.org/hubfs/SR-favicon.svg",
        "Redirect": "https://smartrecovery.org",
        "AbstractSource": "BS4",
        "AbstractURL": "https://smartrecovery.org"
    },
    {
        "link": "https://metorik.com",
        "Heading": "eCommerce Analytics & Email Marketing for WooCommerce & Shopify",
        "Abstract": "Metorik brings real-time store data, analytics, reports and email marketing into one powerful, intuitive tool \u2013 giving you answers to your hardest questions.",
        "Official Site": "https://metorik.com",
        "Icon": "https://metorik.com/img/asset/bWFpbi9zaGFyZS1pbWcvaG9tZS5qcGc/home.jpg?p=seo_pro_og&s=24e1cf221b5d070b2976f8c5d5b7b38b",
        "Redirect": "https://metorik.com",
        "AbstractSource": "BS4",
        "AbstractURL": "https://metorik.com"
    },
    {
        "link": "https://metascan-reflector.ru",
        "Heading": null,
        "Abstract": null,
        "Official Site": "https://metascan-reflector.ru",
        "Icon": "N/A",
        "Redirect": "https://metascan-reflector.ru",
        "AbstractSource": "BS4",
        "AbstractURL": "https://metascan-reflector.ru"
    },
    {
        "link": "https://icalendars.app",
        "Heading": "ICALENDARS",
        "Abstract": null,
        "Official Site": "https://icalendars.app",
        "Icon": "/images/favicon.ico",
        "Redirect": "https://icalendars.app",
        "AbstractSource": "BS4",
        "AbstractURL": "https://icalendars.app"
    },
    {
        "link": "https://whackahack.com",
        "Heading": "    Whack a Hack! - La comunidad de hispana sobre fangames de Pok\u00e9mon\n",
        "Abstract": "La mayor comunidad de Pok\u00e9mon en espa\u00f1ol de hack ROM GBA NDS GBC y fangames RPG disponibles para descargar gratis. Aprende a crear tu propio juego completo de Pok\u00e9mon con herramientas y tutoriales, adem\u00e1s de sprites, tiles, MIDIs, etc.",
        "Official Site": "https://whackahack.com/",
        "Icon": "/uploads/favicon.ico",
        "Redirect": "https://whackahack.com/",
        "AbstractSource": "BS4",
        "AbstractURL": "https://whackahack.com/"
    },
    {
        "link": "https://tribunadonorte.com.br",
        "Heading": "Tribuna do Norte - O maior portal de not\u00edcias do RN",
        "Abstract": "O maior portal de not\u00edcias do RN",
        "Official Site": "https://tribunadonorte.com.br/",
        "Icon": "https://tribunadonorte.com.br/wp-content/uploads/2026/04/favicon-76x76-1.webp",
        "Redirect": "https://tribunadonorte.com.br/",
        "AbstractSource": "BS4",
        "AbstractURL": "https://tribunadonorte.com.br/"
    },
    {
        "link": "https://miniwebtool.com",
        "Heading": "MiniWebtool - Online Tools and Calculators ",
        "Abstract": "We're dedicated to crafting user-friendly online calculators, converters, and utilities, simplifying tasks and enhancing your everyday efficiency.",
        "Official Site": "https://MiniWebtool.com/",
        "Icon": "https://images.miniwebtool.com/en.png",
        "Redirect": "https://MiniWebtool.com/",
        "AbstractSource": "BS4",
        "AbstractURL": "https://MiniWebtool.com/"
    },
    {
        "link": "https://cake-cake.net",
        "Heading": "\u6559\u3048\u305f\u3044\u30b9\u30a4\u30fc\u30c4 | \u65e5\u672c\u5404\u5730\u306e\"\u8ab0\u304b\u306b\u6559\u3048\u305f\u304f\u306a\u308b\u30b9\u30a4\u30fc\u30c4\"\u3092\u53d6\u308a\u4e0a\u3052\u308b\u5c02\u9580\u30e1\u30c7\u30a3\u30a2\uff5c\u304a\u53d6\u308a\u5bc4\u305b\u5546\u54c1\u3084\u5e97\u8217\u9650\u5b9a\u5546\u54c1\u306e\u7d39\u4ecb\u3001\u4f01\u753b\u306a\u3069\u3092\u3084\u3063\u3066\u307e\u3059\u3002",
        "Abstract": "\u65e5\u672c\u5404\u5730\u306e\"\u8ab0\u304b\u306b\u6559\u3048\u305f\u304f\u306a\u308b\u30b9\u30a4\u30fc\u30c4\"\u3092\u53d6\u308a\u4e0a\u3052\u308b\u5c02\u9580\u30e1\u30c7\u30a3\u30a2\uff5c\u304a\u53d6\u308a\u5bc4\u305b\u5546\u54c1\u3084\u5e97\u8217\u9650\u5b9a\u5546\u54c1\u306e\u7d39\u4ecb\u3001\u4f01\u753b\u306a\u3069\u3092\u3084\u3063\u3066\u307e\u3059\u3002",
        "Official Site": "https://cake-cake.net",
        "Icon": "https://www.cake-cake.net/wp-content/uploads/cropped-favicon2.png",
        "Redirect": "https://cake-cake.net",
        "AbstractSource": "BS4",
        "AbstractURL": "https://cake-cake.net"
    },
    {
        "link": "https://winadda.co.in",
        "Heading": "domain_name",
        "Abstract": "Bet with the most trusted online betting exchange in India. Get the best odds, instant withdrawals & deposits, 24/7 customer service and refer bonus. Enjoy safe and secure betting with domain_name.",
        "Official Site": "https://winadda.co.in",
        "Icon": "/assets/icon/favicon.png",
        "Redirect": "https://winadda.co.in",
        "AbstractSource": "BS4",
        "AbstractURL": "https://winadda.co.in"
    },
    {
        "link": "https://firekirin.in",
        "Heading": null,
        "Abstract": null,
        "Official Site": "https://firekirin.in",
        "Icon": "N/A",
        "Redirect": "https://firekirin.in",
        "AbstractSource": "BS4",
        "AbstractURL": "https://firekirin.in"
    },
    {
        "link": "https://gndu.ac.in",
        "Heading": "Redirecting...",
        "Abstract": null,
        "Official Site": "https://gndu.ac.in",
        "Icon": "N/A",
        "Redirect": "https://gndu.ac.in",
        "AbstractSource": "BS4",
        "AbstractURL": "https://gndu.ac.in"
    },
    {
        "link": "https://bgdnes.bg",
        "Heading": "\u0411\u044a\u043b\u0433\u0430\u0440\u0438\u044f \u0414\u043d\u0435\u0441",
        "Abstract": "\u0411\u044a\u043b\u0433\u0430\u0440\u0438\u044f \u0414\u043d\u0435\u0441 \u0432 \u0434\u0435\u043d\u043e\u043d\u043e\u0449\u0438\u0435\u0442\u043e \u043d\u043e\u0432\u0438\u043d\u0438, \u0431\u0438\u0437\u043d\u0435\u0441, \u0430\u043d\u0430\u043b\u0438\u0437\u0438, \u0441\u043f\u043e\u0440\u0442, \u043c\u043d\u0435\u043d\u0438\u044f, \u0438\u043d\u0442\u0435\u0440\u0432\u044e\u0442\u0430, \u0440\u0430\u0437\u0441\u043b\u0435\u0434\u0432\u0430\u043d\u0438\u044f, \u043f\u043e\u043b\u0438\u0442\u0438\u043a\u0430, \u0444\u0443\u0442\u0431\u043e\u043b, \u0440\u0435\u0433\u0438\u043e\u043d\u0430\u043b\u043d\u0438 \u043d\u043e\u0432\u0438\u043d\u0438 \u0438 \u043a\u043e\u043c\u0435\u043d\u0442\u0430\u0440\u0438 \u0441 bgdnes.bg",
        "Official Site": "https://www.bgdnes.bg",
        "Icon": "https://www.bgdnes.bg/images/cache/bgdnes-og.jpg",
        "Redirect": "https://www.bgdnes.bg",
        "AbstractSource": "BS4",
        "AbstractURL": "https://www.bgdnes.bg"
    },
    {
        "link": "https://hacoo.app",
        "Heading": "Hacoo - Sharing Discovering & Inspiring",
        "Abstract": null,
        "Official Site": "https://www.hacoo.app/en-US/",
        "Icon": "/favicon.ico",
        "Redirect": "https://www.hacoo.app/en-US/",
        "AbstractSource": "BS4",
        "AbstractURL": "https://www.hacoo.app/en-US/"
    },
    {
        "link": "https://buildin.ai",
        "Heading": "Buildin \u2014 Your AI Workspace to Build, Manage & Sell",
        "Abstract": null,
        "Official Site": "https://buildin.ai",
        "Icon": "https://cdn2.buildin.ai/assets/og-image.png",
        "Redirect": "https://buildin.ai",
        "AbstractSource": "BS4",
        "AbstractURL": "https://buildin.ai"
    },
    {
        "link": "https://mrsgreenapple.com",
        "Heading": "Mrs. GREEN APPLE OFFICIAL SITE\uff5cOFFICIAL FAN CLUB \u300cRingo Jam\u300d",
        "Abstract": "Mrs. GREEN APPLE\u306e\u30aa\u30d5\u30a3\u30b7\u30e3\u30eb\u30b5\u30a4\u30c8\u30fb\u30d5\u30a1\u30f3\u30af\u30e9\u30d6\u30b5\u30a4\u30c8\u30022024\u5e743\u6708\u30d5\u30eb\u30ea\u30cb\u30e5\u30fc\u30a2\u30eb\u30aa\u30fc\u30d7\u30f3\uff01\u6700\u65b0\u60c5\u5831\u3084\u30d5\u30a1\u30f3\u30af\u30e9\u30d6\u9650\u5b9a\u30c1\u30b1\u30c3\u30c8\u5148\u884c\u53d7\u4ed8\u306a\u3069\u3001\u4eca\u5f8c\u3082\u7d9a\u3005\u3068\u65b0\u30b3\u30f3\u30c6\u30f3\u30c4\u304c\u767b\u5834\u4e88\u5b9a\u3067\u3059\u3002",
        "Official Site": "https://mrsgreenapple.com/",
        "Icon": "https://mrsgreenapple.com/og_image_2026.png",
        "Redirect": "https://mrsgreenapple.com/",
        "AbstractSource": "BS4",
        "AbstractURL": "https://mrsgreenapple.com/"
    },
    {
        "link": "https://nodasoft.com",
        "Heading": "Access Denied",
        "Abstract": null,
        "Official Site": "https://nodasoft.com",
        "Icon": "N/A",
        "Redirect": "https://nodasoft.com",
        "AbstractSource": "BS4",
        "AbstractURL": "https://nodasoft.com"
    },
    {
        "link": "https://localrent.com",
        "Heading": "Car rental in Europe, Asia and Africa \u2014 Localrent.com",
        "Abstract": "A wide selection of cars from local distributors, full pricing transparency, low deposits and round-the-clock support on the road.",
        "Official Site": "https://localrent.com",
        "Icon": "https://www.localrent.com/logos/seo/localrent.jpg",
        "Redirect": "https://localrent.com",
        "AbstractSource": "BS4",
        "AbstractURL": "https://localrent.com"
    },
    {
        "link": "https://rampinteractive.com",
        "Heading": "RAMP InterActive - Your All-in-One Sports Management Solution",
        "Abstract": "Streamline your sport organization with RAMP InterActive's all-in-one sports management solution.",
        "Official Site": "https://www.rampinteractive.com",
        "Icon": "images/logo/favicon.png",
        "Redirect": "https://www.rampinteractive.com",
        "AbstractSource": "BS4",
        "AbstractURL": "https://www.rampinteractive.com"
    },
    {
        "link": "https://contasimple.com",
        "Heading": "Software de Gesti\u00f3n para Aut\u00f3nomos - Programa de Gesti\u00f3n para Pymes",
        "Abstract": "Software de contabilidad y gesti\u00f3n para aut\u00f3nomos, empresas, pymes, gestor\u00edas\u2026 Realiza la gesti\u00f3n integral de la contabilidad de tu negocio con un solo programa.",
        "Official Site": "https://www.contasimple.com/",
        "Icon": "https://www.contasimple.com/wp-content/themes/cegid/assets/dist/images/favicon.ico",
        "Redirect": "https://www.contasimple.com/",
        "AbstractSource": "BS4",
        "AbstractURL": "https://www.contasimple.com/"
    },
    {
        "link": "https://opportunitiesforyouth.org",
        "Heading": "Opportunities for Youth | Empowering Youth through Access to Information and Opportunities",
        "Abstract": null,
        "Official Site": "https://opportunitiesforyouth.org",
        "Icon": "https://i0.wp.com/opportunitiesforyouth.org/wp-content/uploads/2025/02/ofy-00-.jpg",
        "Redirect": "https://opportunitiesforyouth.org",
        "AbstractSource": "BS4",
        "AbstractURL": "https://opportunitiesforyouth.org"
    },
    {
        "link": "https://rankingoo.net",
        "Heading": "\u30e9\u30f3\u30ad\u30f3\u30b0\u30fc\uff01 | \u307f\u3093\u306a\u306e\u300c\u3061\u3087\u3063\u3068\u6c17\u306b\u306a\u308b\u300d\u3092\u8abf\u3079\u305f\u30e9\u30f3\u30ad\u30f3\u30b0\u30b5\u30a4\u30c8",
        "Abstract": "\u30e9\u30f3\u30ad\u30f3\u30b0\u30fc\uff01\u306f\u3001\u6700\u5927\u7d041\u4e07\u4eba\u304c\u6295\u7968\u3059\u308b\u306a\u3093\u3067\u3082\u30e9\u30f3\u30ad\u30f3\u30b0\u30b5\u30a4\u30c8\u3002\u4ff3\u512a\u30fb\u5973\u512a\u3084\u6620\u753b\u30fb\u30c9\u30e9\u30de\u3001\u30a2\u30cb\u30e1\u3001\u97d3\u56fd\u82b8\u80fd\u3001\u5730\u57df\u30cd\u30bf\u3001\u304a\u3082\u3057\u308d\u30cd\u30bf\u306a\u3069\u2026\u8272\u3005\u30e9\u30f3\u30ad\u30f3\u30b0\uff01\u7dcf\u6570\u7d045000\u306e\u7d50\u679c\u767a\u8868\u306b\u306f\u30e6\u30fc\u30b6\u30fc\u30dc\u30a4\u30b9\u3082\u3002",
        "Official Site": "https://rankingoo.net/",
        "Icon": "https://rankingoo.net/wp-content/uploads/2024/01/cropped-icon.png",
        "Redirect": "https://rankingoo.net/",
        "AbstractSource": "BS4",
        "AbstractURL": "https://rankingoo.net/"
    },
    {
        "link": "https://aax.com",
        "Heading": "Welcome to nginx!",
        "Abstract": null,
        "Official Site": "https://aax.com",
        "Icon": "N/A",
        "Redirect": "https://aax.com",
        "AbstractSource": "BS4",
        "AbstractURL": "https://aax.com"
    },
    {
        "link": "https://jollyroom.se",
        "Heading": "Jollyroom.se | Nordens st\u00f6rsta barn- & babybutik online",
        "Abstract": "P\u00e5 Jollyroom hittar du allt f\u00f6r barnfamiljen. K\u00f6p barnvagnar, bilstolar, barnkl\u00e4der, leksaker, barnm\u00f6bler, baby- och gravidprodukter till l\u00e5ga priser.",
        "Official Site": "https://www.jollyroom.se/",
        "Icon": "/favicon.ico",
        "Redirect": "https://www.jollyroom.se/",
        "AbstractSource": "BS4",
        "AbstractURL": "https://www.jollyroom.se/"
    }
]